Workbook

Sheet Director
A1: 2025 Year to Date
A2: AM | B2: (All)
A3: Text Code | B3: (All)
A4: Company | B4: (All)
A5: Vendor | B5: (All)
A7: Director | B7: Variance | C7: Booked | D7: As a % of Booked
A8: Owen Cunningham | B8: 145326.89 | C8: 12556381 | D8: 0.0028160455
A9: Olivia Gorfain | B9: 78196.72 | C9: 16189253 | D9: 0.0019016387
A10: Norma Lopez | B10: 49175.93 | C10: 6933299.7 | D10: 0.0036749827
A11: Jill Marsh | B11: 48648.31 | C11: 5820005.6 | D11: 0.0063324304
A12: Lela Huenergardt | B12: 42378.55 | C12: 3648805.2 | D12: 0.0063121541
A13: Simon Sheppard | B13: 36991.48 | C13: 837514.92 | D13: 0.033716141
A14: Kate Ingelstrom | B14: 33362.16 | C14: 2470161 | D14: 0.014841832
A15: Chris Cicisly | B15: 31118.41 | C15: 6857499.4 | D15: 0.0036014806
A16: Nick Christianson | B16: 21374.35 | C16: 960059.98 | D16: 0.053008469
A17: Mark Dailey | B17: 16795.47 | C17: 1674828.1 | D17: 0.018921085
A18: Z-Stephanie Hawkins | B18: 12330.58 | C18: 0 | D18: 0
A19: Troy Ocariza | B19: 12155.24 | C19: 863078.52 | D19: 0.024708044
... A33: Paul Razo | B33: 128.31 | C33: 288491.56 | D33: 0.044476171
A34: Torrey Carroll | B34: 100 | C34: #N/A | D34: 0
A35: Z-Denelle Bourgeois | B35: 90 | C35: 0 | D35: 0
A36: Frankie Kim | B36: 10 | C36: #N/A | D36: 0
A37: Grand Total | B37: 566154.8 | C37: #N/A | D37: 0

Sheet Account Manager
A1: 2025 Year to Date
A2: Salesperson | B2: (All)
A3: Text Code | B3: (All)
A4: Company | B4: (All)
A5: Vendor | B5: (All)
A7: AM | B7: Variance
A8: Carina Collison | B8: 51773.7
A9: Lindsay Hanief | B9: 51286.99
A10: Josie Maitlen,Torrey Crell | B10: 40812.91
A11: Norma Lopez | B11: 38798.67
A12: Patty Medina | B12: 37094.89
A13: Kimi Katsuyoshi | B13: 30792.11
A14: Farrah Race | B14: 30149.74
A15: Frances Kim | B15: 28344.4
A16: Megan Ewers | B16: 26218.37
A17: Jenni Lombardi | B17: 22502.13
A18: Genesis Rita | B18: 21685.02
A19: Mary Sparacino | B19: 19011.43
... A88: Anthony Pantaleoni,Melissa Rokes | B88: -218.55
B89: -219.4
A90: Intuit-OR 205 | B90: -219.4
A91: 93472 | B91: -219.4
A92: addt shipping charges to get the fabric sooner | B92: 63.98
A93: Credit Line Added to Match Acknowledgement | B93: -283.38
A94: Saoirse O'Connor | B94: -557.31
A95: Casey Fleming,Norma Lopez | B95: -908
A96: Andrea Greever | B96: -2852.54
A97: Chryslyn Perkins | B97: -4623.57
A98: Grand Total | B98: 566154.8

Sheet Type
A1: 2025 Year to Date
A2: Salesperson | B2: (All)
A3: AM | B3: (All)
A4: Company | B4: (All)
A5: Customer | B5: (All)
A6: Vendor | B6: (All)
A8: Error Type | B8: Variance
A9: Specification Error | B9: 253067.95
A10: Miscellaneous | B10: 127976.01
A11: Customer Accomodation | B11: 115818.83
A12: Shipping Charges | B12: 36880.75
A13: Vendor Caused | B13: 32411.26
A14: Grand Total | B14: 566154.8

Sheet Office
A1: 2025 Year to Date
A2: Office | B2: Variance
A3: San Francisco | B3: 323716.74
A4: San Jose | B4: 190525.05
A5: Sacramento | B5: 51913.01
A6: Grand Total | B6: 566154.8

Sheet Top 10 Vendors
A1: 2025 Year to Date
A2: Vendor | B2: Variance
A3: SERVICE - Service West- San Leandro | B3: 65517.56
A4: KNO - Knoll, Inc. | B4: 62470.09
A5: HMI - Herman Miller | B5: 57915.22
A6: ADRIANI - Adrian Inc. - Stations San Jose | B6: 21363.92
A7: ABSFACI - ABS Facility Services, Inc. | B7: 16237.48
A8: ALLMODU - Allmodular Systems, Inc. | B8: 14213.76
A9: TBD - TBD | B9: 13710.25
A10: ARD - Arcadia | B10: 12464.63
A11: COMMERC04 - Commercial Interiors West, Inc. | B11: 12114.2
A12: GEI - Geiger International, Inc. | B12: 11094.1
A13: Grand Total | B13: 287101.21

Sheet Top 10 Clients
A1: 2025 Year to Date
A2: Client | B2: Variance | C2: As a % of Booked
A3: Samuel Merritt University | B3: 54265.42 | C3: 0.046058879
A4: Intuit-OR 205 | B4: 42046.21 | C4: 0.0051613126
A5: Levi Strauss & Co | B5: 31376.33 | C5: 0.12245429
A6: Altos Labs, Inc. | B6: 23627.85 | C6: 0.039655072
A7: Sequoia Capital Operations, LLC | B7: 22031.39 | C7: 0.0079424929
A8: Davis Polk & Wardwell LLP | B8: 20314.9 | C8: 0.14636696
A9: Orrick, Herrington & Sutcliffe LLP | B9: 16675.42 | C9: 0.0095515881
A10: Stanford University | B10: 15194.74 | C10: 0.0087950207
A11: Peregrine Technologies, Inc. | B11: 14906.75 | C11: 0.35905325
A12: San Francisco State University | B12: 13461.99 | C12: 0
A13: Grand Total | B13: 253901 | C13: 0.015291271

Sheet Data
A1: Line Item Text Listing
A2: Order | B2: Line # | C2: Salesperson | D2: Customer | E2: Product ID | F2: Product Description | G2: OPC | H2: Line Item Text Code | I2: Line Item Text Code Description | J2: Company | K2: Vendor | L2: QTY | M2: Ext. Sell | N2: Ext. Cost | O2: Misc. Code | P2: Text Code | Q2: Profit Loss | R2: Bookings | S2: Client Bookings | T2: AM
A3: 73180 | B3: 283 | C3: Mark Dailey | D3: NetApp | E3: WAREHOUSE STORAGE | F3: Warehouse Storage Nov For fibre chairs, stools & side chairs | G3: STORE | H3: MISC | I3: Storage | J3: San Jose | K3: SERVICE - Service West- San Leandro | L3: 1 | M3: 0 | N3: 264.6 | O3: Shanna Dollarhide | P3: =VLOOKUP(Table1[[#This Row],[Line Item Text Code]],$U$3:$V$7,2,FALSE) -> Miscellaneous | Q3: =Table1[[#This Row],[Ext. Cost]]-Table1[[#This Row],[Ext. Sell]] -> 264.6 | R3: =VLOOKUP(C3,Bookings!$A$1:$B$33,2,FALSE) -> 1917863.2 | S3: =IFERROR(VLOOKUP(D3,Bookings!E:F,2,FALSE),0) -> 0 | T3: =IFERROR(VLOOKUP(Table1[[#This Row],[Order]],Bookings_with_AM_Report!A:L,12,FALSE),"N/A") -> Norma Lopez | U3: MISC | V3: Miscellaneous
A4: 73180 | B4: 284 | C4: Mark Dailey | D4: NetApp | E4: WAREHOUSE STORAGE | F4: Warehouse Storage Jan For fibre chairs, stools & side chairs | G4: STORE | H4: MISC | I4: Storage | J4: San Jose | K4: SERVICE - Service West- San Leandro | L4: 1 | M4: 0 | N4: 264.6 | O4: Shanna Dollarhide | P4: =VLOOKUP(Table1[[#This Row],[Line Item Text Code]],$U$3:$V$7,2,FALSE) -> Miscellaneous | Q4: =Table1[[#This Row],[Ext. Cost]]-Table1[[#This Row],[Ext. Sell]] -> 264.6 | R4: =VLOOKUP(C4,Bookings!$A$1:$B$33,2,FALSE) -> 1917863.2 | S4: =IFERROR(VLOOKUP(D4,Bookings!E:F,2,FALSE),0) -> 0 | T4: =IFERROR(VLOOKUP(Table1[[#This Row],[Order]],Bookings_with_AM_Report!A:L,12,FALSE),"N/A") -> Norma Lopez | U4: CUST | V4: Customer Accomodation
A5: 73180 | B5: 285 | C5: Mark Dailey | D5: NetApp | E5: WAREHOUSE STORAGE | F5: Warehouse Storage Feb For fibre chairs, stools & side chairs | G5: STORE | H5: MISC | I5: Storage | J5: San Jose | K5: SERVICE - Service West- San Leandro | L5: 1 | M5: 0 | N5: 264.6 | O5: Shanna Dollarhide | P5: =VLOOKUP(Table1[[#This Row],[Line Item Text Code]],$U$3:$V$7,2,FALSE) -> Miscellaneous | Q5: =Table1[[#This Row],[Ext. Cost]]-Table1[[#This Row],[Ext. Sell]] -> 264.6 | R5: =VLOOKUP(C5,Bookings!$A$1:$B$33,2,FALSE) -> 1917863.2 | S5: =IFERROR(VLOOKUP(D5,Bookings!E:F,2,FALSE),0) -> 0 | T5: =IFERROR(VLOOKUP(Table1[[#This Row],[Order]],Bookings_with_AM_Report!A:L,12,FALSE),"N/A") -> Norma Lopez | U5: SHIP | V5: Shipping Charges
A6: 73180 | B6: 286 | C6: Mark Dailey | D6: NetApp | E6: WAREHOUSE STORAGE | F6: Warehouse Storage March For fibre chairs, stools & side chairs | G6: STORE | H6: MISC | I6: Storage | J6: San Jose | K6: SERVICE - Service West- San Leandro | L6: 1 | M6: 0 | N6: 264.6 | O6: Shanna Dollarhide | P6: =VLOOKUP(Table1[[#This Row],[Line Item Text Code]],$U$3:$V$7,2,FALSE) -> Miscellaneous | Q6: =Table1[[#This Row],[Ext. Cost]]-Table1[[#This Row],[Ext. Sell]] -> 264.6 | R6: =VLOOKUP(C6,Bookings!$A$1:$B$33,2,FALSE) -> 1917863.2 | S6: =IFERROR(VLOOKUP(D6,Bookings!E:F,2,FALSE),0) -> 0 | T6: =IFERROR(VLOOKUP(Table1[[#This Row],[Order]],Bookings_with_AM_Report!A:L,12,FALSE),"N/A") -> Norma Lopez | U6: SPEC | V6: Specification Error
A7: 73180 | B7: 287 | C7: Mark Dailey | D7: NetApp | E7: WAREHOUSE STORAGE | F7: Warehouse Storage April For fibre chairs, stools & side chairs | G7: STORE | H7: MISC | I7: Storage | J7: San Jose | K7: SERVICE - Service West- San Leandro | L7: 1 | M7: 0 | N7: 264.6 | O7: Shanna Dollarhide | P7: =VLOOKUP(Table1[[#This Row],[Line Item Text Code]],$U$3:$V$7,2,FALSE) -> Miscellaneous | Q7: =Table1[[#This Row],[Ext. Cost]]-Table1[[#This Row],[Ext. Sell]] -> 264.6 | R7: =VLOOKUP(C7,Bookings!$A$1:$B$33,2,FALSE) -> 1917863.2 | S7: =IFERROR(VLOOKUP(D7,Bookings!E:F,2,FALSE),0) -> 0 | T7: =IFERROR(VLOOKUP(Table1[[#This Row],[Order]],Bookings_with_AM_Report!A:L,12,FALSE),"N/A") -> Norma Lopez | U7: VEN | V7: Vendor Caused
A8: 73180 | B8: 288 | C8: Mark Dailey | D8: NetApp | E8: WAREHOUSE STORAGE | F8: Warehouse Storage May For fibre chairs, stools & side chairs | G8: STORE | H8: MISC | I8: Storage | J8: San Jose | K8: SERVICE - Service West- San Leandro | L8: 1 | M8: 0 | N8: 264.6 | O8: Shanna Dollarhide | P8: =VLOOKUP(Table1[[#This Row],[Line Item Text Code]],$U$3:$V$7,2,FALSE) -> Miscellaneous | Q8: =Table1[[#This Row],[Ext. Cost]]-Table1[[#This Row],[Ext. Sell]] -> 264.6 | R8: =VLOOKUP(C8,Bookings!$A$1:$B$33,2,FALSE) -> 1917863.2 | S8: =IFERROR(VLOOKUP(D8,Bookings!E:F,2,FALSE),0) -> 0 | T8: =IFERROR(VLOOKUP(Table1[[#This Row],[Order]],Bookings_with_AM_Report!A:L,12,FALSE),"N/A") -> Norma Lopez
A9: 73180 | B9: 289 | C9: Mark Dailey | D9: NetApp | E9: WAREHOUSE STORAGE | F9: Warehouse Storage June For fibre chairs, stools & side chairs | G9: STORE | H9: MISC | I9: Storage | J9: San Jose | K9: SERVICE - Service West- San Leandro | L9: 1 | M9: 0 | N9: 264.6 | O9: Shanna Dollarhide | P9: =VLOOKUP(Table1[[#This Row],[Line Item Text Code]],$U$3:$V$7,2,FALSE) -> Miscellaneous | Q9: =Table1[[#This Row],[Ext. Cost]]-Table1[[#This Row],[Ext. Sell]] -> 264.6 | R9: =VLOOKUP(C9,Bookings!$A$1:$B$33,2,FALSE) -> 1917863.2 | S9: =IFERROR(VLOOKUP(D9,Bookings!E:F,2,FALSE),0) -> 0 | T9: =IFERROR(VLOOKUP(Table1[[#This Row],[Order]],Bookings_with_AM_Report!A:L,12,FALSE),"N/A") -> Norma Lopez
A10: 73180 | B10: 290 | C10: Mark Dailey | D10: NetApp | E10: WAREHOUSE STORAGE | F10: Warehouse Storage July For fibre chairs, stools & side chairs | G10: STORE | H10: MISC | I10: Storage | J10: San Jose | K10: SERVICE - Service West- San Leandro | L10: 1 | M10: 0 | N10: 264.6 | O10: Shanna Dollarhide | P10: =VLOOKUP(Table1[[#This Row],[Line Item Text Code]],$U$3:$V$7,2,FALSE) -> Miscellaneous | Q10: =Table1[[#This Row],[Ext. Cost]]-Table1[[#This Row],[Ext. Sell]] -> 264.6 | R10: =VLOOKUP(C10,Bookings!$A$1:$B$33,2,FALSE) -> 1917863.2 | S10: =IFERROR(VLOOKUP(D10,Bookings!E:F,2,FALSE),0) -> 0 | T10: =IFERROR(VLOOKUP(Table1[[#This Row],[Order]],Bookings_with_AM_Report!A:L,12,FALSE),"N/A") -> Norma Lopez
A11: 78772 | B11: 179 | C11: Jill Marsh | D11: Folger Levin | E11: Rebill-Oustanding balace | F11: Remaining balance due for invoice 5213711 | G11: PRO | H11: MISC | I11: Inv 5213711 was partially paid leaving the balance of $577.00 Past Due. | J11: San Francisco | K11: KNO - Knoll, Inc. | L11: 1 | M11: 0 | N11: 577 | O11: Nicole Lentini | P11: =VLOOKUP(Table1[[#This Row],[Line Item Text Code]],$U$3:$V$7,2,FALSE) -> Miscellaneous | Q11: =Table1[[#This Row],[Ext. Cost]]-Table1[[#This Row],[Ext. Sell]] -> 577 | R11: =VLOOKUP(C11,Bookings!$A$1:$B$33,2,FALSE) -> 6210075.2 | S11: =IFERROR(VLOOKUP(D11,Bookings!E:F,2,FALSE),0) -> 0 | T11: =IFERROR(VLOOKUP(Table1[[#This Row],[Order]],Bookings_with_AM_Report!A:L,12,FALSE),"N/A") -> Patty Medina
A12: 80461 | B12: 123 | C12: Lela Huenergardt | D12: County of Santa Clara | E12: FABRICATION | F12: Price to go to site during normal business hours, drill & install (2) new lock assemblies for a storage cabinet already at site. All hardware will be provided by KBM. Does not include any permits. | G12: FABR | H12: CUST | I12: adjusting the locks for the client. | J12: San Jose | K12: ALLMODU - Allmodular Systems, Inc. | L12: 1 | M12: 0 | N12: 845 | O12: Marlene Dyson | P12: =VLOOKUP(Table1[[#This Row],[Line Item Text Code]],$U$3:$V$7,2,FALSE) -> Customer Accomodation | Q12: =Table1[[#This Row],[Ext. Cost]]-Table1[[#This Row],[Ext. Sell]] -> 845 | R12: =VLOOKUP(C12,Bookings!$A$1:$B$33,2,FALSE) -> 3879926.5 | S12: =IFERROR(VLOOKUP(D12,Bookings!E:F,2,FALSE),0) -> 435136.95 | T12: =IFERROR(VLOOKUP(Table1[[#This Row],[Order]],Bookings_with_AM_Report!A:L,12,FALSE),"N/A") -> Megan Ewers
A13: 80461 | B13: 124 | C13: Lela Huenergardt | D13: County of Santa Clara | E13: FABRICATION | F13: Return Trip/Punch trips | G13: FABR | H13: MISC | I13: Labor | J13: San Jose | K13: ALLMODU - Allmodular Systems, Inc. | L13: 1 | M13: 0 | N13: 960 | O13: Marlene Dyson | P13: =VLOOKUP(Table1[[#This Row],[Line Item Text Code]],$U$3:$V$7,2,FALSE) -> Miscellaneous | Q13: =Table1[[#This Row],[Ext. Cost]]-Table1[[#This Row],[Ext. Sell]] -> 960 | R13: =VLOOKUP(C13,Bookings!$A$1:$B$33,2,FALSE) -> 3879926.5 | S13: =IFERROR(VLOOKUP(D13,Bookings!E:F,2,FALSE),0) -> 435136.95 | T13: =IFERROR(VLOOKUP(Table1[[#This Row],[Order]],Bookings_with_AM_Report!A:L,12,FALSE),"N/A") -> Megan Ewers
A14: 80677 | B14: 170 | C14: Lela Huenergardt | D14: Peninsula Health Care District | E14: Workrite | F14: Workrite off set credit received ? | G14: PRO | H14: VEN | I14: Vendor sent a credit out of the blue. MD | J14: San Jose | K14: WRT - Workrite Ergonomics, LLC | L14: 1 | M14: 0 | N14: 128.49 | O14: Marlene Dyson | P14: =VLOOKUP(Table1[[#This Row],[Line Item Text Code]],$U$3:$V$7,2,FALSE) -> Vendor Caused | Q14: =Table1[[#This Row],[Ext. Cost]]-Table1[[#This Row],[Ext. Sell]] -> 128.49 | R14: =VLOOKUP(C14,Bookings!$A$1:$B$33,2,FALSE) -> 3879926.5 | S14: =IFERROR(VLOOKUP(D14,Bookings!E:F,2,FALSE),0) -> 0 | T14: =IFERROR(VLOOKUP(Table1[[#This Row],[Order]],Bookings_with_AM_Report!A:L,12,FALSE),"N/A") -> N/A
A15: 81432 | B15: 23 | C15: Lela Huenergardt | D15: County of Santa Clara | E15: WAREHOUSE STORAGE | F15: Storage Dates: 01/04/25 to 02/03/25 Order: KBMH228301 - Saint Louise Regional Hospital - Pharmacy *QTE* PO# 81432-90107 Receiving# KBMH228301.05 (1) Pallet Positions Date Received:12/05/2024 Customer PO #: 81432-90107 Manufacturer: Workrite Product PO#: 81432-90106 Product Received: (3) Height Adj Bases | G15: STORE | H15: CUST | I15: Lela working with client on storage. | J15: San Jose | K15: JEISANJ - JEI | L15: 1 | M15: 0 | N15: 38 | O15: Marlene Dyson | P15: =VLOOKUP(Table1[[#This Row],[Line Item Text Code]],$U$3:$V$7,2,FALSE) -> Customer Accomodation | Q15: =Table1[[#This Row],[Ext. Cost]]-Table1[[#This Row],[Ext. Sell]] -> 38 | R15: =VLOOKUP(C15,Bookings!$A$1:$B$33,2,FALSE) -> 3879926.5 | S15: =IFERROR(VLOOKUP(D15,Bookings!E:F,2,FALSE),0) -> 435136.95 | T15: =IFERROR(VLOOKUP(Table1[[#This Row],[Order]],Bookings_with_AM_Report!A:L,12,FALSE),"N/A") -> Megan Ewers
A16: 81432 | B16: 24 | C16: Lela Huenergardt | D16: County of Santa Clara | E16: WAREHOUSE STORAGE | F16: Storage Dates: 1/12/25 - 2/11/25 Order: KBMH228301 - Saint Louise Regional Hospital - Pharmacy *QTE* PO# 81432-90107 Receiving# KBMH228301.01 (1) Pallet Positions Date Received:11/11/2024 Customer PO #: 81432-90107 Manufacturer: Grainger Product PO#: 81432-90102 Product Received: (1) Utility Cart Receiving# KBMH228301.02 (1) Carton Date Received:11/12/2024 Customer PO #: 81432-90107 Manufacturer: Grainger Product PO#: 81432-90102 Product Received: (2) Stools Receiving# KBMH228301.03 (1) Pallet Positions Date Received:11/12/2024 Customer PO #: 81432-90107 Manufacturer: Grainger Product PO#: 81432-90102 Product Received: (1) Lateral File | G16: STORE | H16: MISC | I16: Storage | J16: San Jose | K16: JEISANJ - JEI | L16: 1 | M16: 0 | N16: 91 | O16: Marlene Dyson | P16: =VLOOKUP(Table1[[#This Row],[Line Item Text Code]],$U$3:$V$7,2,FALSE) -> Miscellaneous | Q16: =Table1[[#This Row],[Ext. Cost]]-Table1[[#This Row],[Ext. Sell]] -> 91 | R16: =VLOOKUP(C16,Bookings!$A$1:$B$33,2,FALSE) -> 3879926.5 | S16: =IFERROR(VLOOKUP(D16,Bookings!E:F,2,FALSE),0) -> 435136.95 | T16: =IFERROR(VLOOKUP(Table1[[#This Row],[Order]],Bookings_with_AM_Report!A:L,12,FALSE),"N/A") -> Megan Ewers
A17: 81432 | B17: 25 | C17: Lela Huenergardt | D17: County of Santa Clara | E17: WAREHOUSE STORAGE | F17: Storage Dates: 1/20/24 to 02/19/25 Order: KBMH228301 - Saint Louise Regional Hospital - Pharmacy *QTE* PO# 81432-90107 Receiving# KBMH228301.04 (1) Pallet Positions Date Received:11/20/2024 Customer PO #: 81432-90107 Manufacturer: Eagle Group Product PO#: 81432-90102 Product Received: (2) Gowning Bench $36.00 | G17: STORE | H17: MISC | I17: Storage | J17: San Jose | K17: JEISANJ - JEI | L17: 1 | M17: 0 | N17: 38 | O17: Marlene Dyson | P17: =VLOOKUP(Table1[[#This Row],[Line Item Text Code]],$U$3:$V$7,2,FALSE) -> Miscellaneous | Q17: =Table1[[#This Row],[Ext. Cost]]-Table1[[#This Row],[Ext. Sell]] -> 38 | R17: =VLOOKUP(C17,Bookings!$A$1:$B$33,2,FALSE) -> 3879926.5 | S17: =IFERROR(VLOOKUP(D17,Bookings!E:F,2,FALSE),0) -> 435136.95 | T17: =IFERROR(VLOOKUP(Table1[[#This Row],[Order]],Bookings_with_AM_Report!A:L,12,FALSE),"N/A") -> Megan Ewers
A18: 81432 | B18: 26 | C18: Lela Huenergardt | D18: County of Santa Clara | E18: WAREHOUSE STORAGE | F18: Storage Dates: 01/25/25 to 02/24/25 Order: KBMH228301 - Saint Louise Regional Hospital - Pharmacy *QTE* PO# 81432-90107 Receiving# KBMH228301.06 (2) Pieces Date Received:12/26/2024 Customer PO #: 81432-90107 Manufacturer: Knoll Product PO#: 81432-90103 Product Received: (2) Rectangular Tops | G18: STORE | H18: MISC | I18: Storage | J18: San Jose | K18: JEISANJ - JEI | L18: 1 | M18: 0 | N18: 15 | O18: Marlene Dyson | P18: =VLOOKUP(Table1[[#This Row],[Line Item Text Code]],$U$3:$V$7,2,FALSE) -> Miscellaneous | Q18: =Table1[[#This Row],[Ext. Cost]]-Table1[[#This Row],[Ext. Sell]] -> 15 | R18: =VLOOKUP(C18,Bookings!$A$1:$B$33,2,FALSE) -> 3879926.5 | S18: =IFERROR(VLOOKUP(D18,Bookings!E:F,2,FALSE),0) -> 435136.95 | T18: =IFERROR(VLOOKUP(Table1[[#This Row],[Order]],Bookings_with_AM_Report!A:L,12,FALSE),"N/A") -> Megan Ewers
A19: 81432 | B19: 27 | C19: Lela Huenergardt | D19: County of Santa Clara | E19: WAREHOUSE STORAGE | F19: Storage Dates: 02/04/25 - 3/3/25 Order: KBMH228301 - Saint Louise Regional Hospital - Pharmacy *QTE* PO# 81432-90107 Receiving# KBMH228301.05 (1) Pallet Positions Date Received:12/05/2024 Customer PO #: 81432-90107 Manufacturer: Workrite Product PO#: 81432-90106 Product Received: (3) Height Adj Bases | G19: STORE | H19: CUST | I19: Lela working with client on storage. | J19: San Jose | K19: JEISANJ - JEI | L19: 1 | M19: 0 | N19: 38 | O19: Marlene Dyson | P19: =VLOOKUP(Table1[[#This Row],[Line Item Text Code]],$U$3:$V$7,2,FALSE) -> Customer Accomodation | Q19: =Table1[[#This Row],[Ext. Cost]]-Table1[[#This Row],[Ext. Sell]] -> 38 | R19: =VLOOKUP(C19,Bookings!$A$1:$B$33,2,FALSE) -> 3879926.5 | S19: =IFERROR(VLOOKUP(D19,Bookings!E:F,2,FALSE),0) -> 435136.95 | T19: =IFERROR(VLOOKUP(Table1[[#This Row],[Order]],Bookings_with_AM_Report!A:L,12,FALSE),"N/A") -> Megan Ewers
... A70: 82999 | B70: 70 | C70: Simon Sheppard | D70: Tri Pointe Homes Holdings, Inc | E70: KBM-PM | F70: PROJECT MANAGER | G70: PM-TAX | H70: MISC | I70: True-Up | J70: Sacramento | K70: KBM-PM - KBM-Hogue Project Management | L70: 1 | M70: 0 | N70: 1275 | O70: Marcus Freeman | P70: =VLOOKUP(Table1[[#This Row],[Line Item Text Code]],$U$3:$V$7,2,FALSE) -> Miscellaneous | Q70: =Table1[[#This Row],[Ext. Cost]]-Table1[[#This Row],[Ext. Sell]] -> 1275 | R70: =VLOOKUP(C70,Bookings!$A$1:$B$33,2,FALSE) -> 893520.77 | S70: =IFERROR(VLOOKUP(D70,Bookings!E:F,2,FALSE),0) -> 121573.87 | T70: =IFERROR(VLOOKUP(Table1[[#This Row],[Order]],Bookings_with_AM_Report!A:L,12,FALSE),"N/A") -> N/A
A71: 83085 | B71: 9 | C71: Owen Cunningham | D71: Sequoia Capital Operations, LLC | E71: MILEAGE | G71: TRV | H71: MISC | I71: Mileage | J71: San Francisco | K71: ASTOR - Astor Ng | L71: 1 | M71: 0 | N71: 30.96 | O71: Kelly Caplan | P71: =VLOOKUP(Table1[[#This Row],[Line Item Text Code]],$U$3:$V$7,2,FALSE) -> Miscellaneous | Q71: =Table1[[#This Row],[Ext. Cost]]-Table1[[#This Row],[Ext. Sell]] -> 30.96 | R71: =VLOOKUP(C71,Bookings!$A$1:$B$33,2,FALSE) -> 13189792 | S71: =IFERROR(VLOOKUP(D71,Bookings!E:F,2,FALSE),0) -> 1874548.9 | T71: =IFERROR(VLOOKUP(Table1[[#This Row],[Order]],Bookings_with_AM_Report!A:L,12,FALSE),"N/A") -> Kimi Katsuyoshi
A72: 83085 | B72: 10 | C72: Owen Cunningham | D72: Sequoia Capital Operations, LLC | E72: MILEAGE | G72: TRV | H72: MISC | I72: Mileage | J72: San Francisco | K72: ASTOR - Astor Ng | L72: 1 | M72: 0 | N72: 18.59 | O72: Kelly Caplan | P72: =VLOOKUP(Table1[[#This Row],[Line Item Text Code]],$U$3:$V$7,2,FALSE) -> Miscellaneous | Q72: =Table1[[#This Row],[Ext. Cost]]-Table1[[#This Row],[Ext. Sell]] -> 18.59 | R72: =VLOOKUP(C72,Bookings!$A$1:$B$33,2,FALSE) -> 13189792 | S72: =IFERROR(VLOOKUP(D72,Bookings!E:F,2,FALSE),0) -> 1874548.9 | T72: =IFERROR(VLOOKUP(Table1[[#This Row],[Order]],Bookings_with_AM_Report!A:L,12,FALSE),"N/A") -> Kimi Katsuyoshi
A73: 83085 | B73: 11 | C73: Owen Cunningham | D73: Sequoia Capital Operations, LLC | E73: MILEAGE | G73: TRV | H73: MISC | I73: Mileage | J73: San Francisco | K73: ASTOR - Astor Ng | L73: 1 | M73: 0 | N73: 25.32 | O73: Kelly Caplan | P73: =VLOOKUP(Table1[[#This Row],[Line Item Text Code]],$U$3:$V$7,2,FALSE) -> Miscellaneous | Q73: =Table1[[#This Row],[Ext. Cost]]-Table1[[#This Row],[Ext. Sell]] -> 25.32 | R73: =VLOOKUP(C73,Bookings!$A$1:$B$33,2,FALSE) -> 13189792 | S73: =IFERROR(VLOOKUP(D73,Bookings!E:F,2,FALSE),0) -> 1874548.9 | T73: =IFERROR(VLOOKUP(Table1[[#This Row],[Order]],Bookings_with_AM_Report!A:L,12,FALSE),"N/A") -> Kimi Katsuyoshi
A74: 83085 | B74: 12 | C74: Owen Cunningham | D74: Sequoia Capital Operations, LLC | E74: MILEAGE | G74: TRV | H74: MISC | I74: Mileage | J74: San Francisco | K74: ASTOR - Astor Ng | L74: 1 | M74: 0 | N74: 25.74 | O74: Kelly Caplan | P74: =VLOOKUP(Table1[[#This Row],[Line Item Text Code]],$U$3:$V$7,2,FALSE) -> Miscellaneous | Q74: =Table1[[#This Row],[Ext. Cost]]-Table1[[#This Row],[Ext. Sell]] -> 25.74 | R74: =VLOOKUP(C74,Bookings!$A$1:$B$33,2,FALSE) -> 13189792 | S74: =IFERROR(VLOOKUP(D74,Bookings!E:F,2,FALSE),0) -> 1874548.9 | T74: =IFERROR(VLOOKUP(Table1[[#This Row],[Order]],Bookings_with_AM_Report!A:L,12,FALSE),"N/A") -> Kimi Katsuyoshi
A75: 83085 | B75: 13 | C75: Owen Cunningham | D75: Sequoia Capital Operations, LLC | E75: MILEAGE | G75: TRV | H75: MISC | I75: Mileage | J75: San Francisco | K75: ASTOR - Astor Ng | L75: 1 | M75: 0 | N75: 25.32 | O75: Kelly Caplan | P75: =VLOOKUP(Table1[[#This Row],[Line Item Text Code]],$U$3:$V$7,2,FALSE) -> Miscellaneous | Q75: =Table1[[#This Row],[Ext. Cost]]-Table1[[#This Row],[Ext. Sell]] -> 25.32 | R75: =VLOOKUP(C75,Bookings!$A$1:$B$33,2,FALSE) -> 13189792 | S75: =IFERROR(VLOOKUP(D75,Bookings!E:F,2,FALSE),0) -> 1874548.9 | T75: =IFERROR(VLOOKUP(Table1[[#This Row],[Order]],Bookings_with_AM_Report!A:L,12,FALSE),"N/A") -> Kimi Katsuyoshi
A76: 83085 | B76: 14 | C76: Owen Cunningham | D76: Sequoia Capital Operations, LLC | E76: MILEAGE | G76: TRV | H76: MISC | I76: Mileage | J76: San Francisco | K76: ASTOR - Astor Ng | L76: 1 | M76: 0 | N76: 6.44 | O76: Kelly Caplan | P76: =VLOOKUP(Table1[[#This Row],[Line Item Text Code]],$U$3:$V$7,2,FALSE) -> Miscellaneous | Q76: =Table1[[#This Row],[Ext. Cost]]-Table1[[#This Row],[Ext. Sell]] -> 6.44 | R76: =VLOOKUP(C76,Bookings!$A$1:$B$33,2,FALSE) -> 13189792 | S76: =IFERROR(VLOOKUP(D76,Bookings!E:F,2,FALSE),0) -> 1874548.9 | T76: =IFERROR(VLOOKUP(Table1[[#This Row],[Order]],Bookings_with_AM_Report!A:L,12,FALSE),"N/A") -> Kimi Katsuyoshi
A77: 83085 | B77: 15 | C77: Owen Cunningham | D77: Sequoia Capital Operations, LLC | E77: MILEAGE | G77: TRV | H77: MISC | I77: Mileage | J77: San Francisco | K77: ASTOR - Astor Ng | L77: 1 | M77: 0 | N77: 25.32 | O77: Kelly Caplan | P77: =VLOOKUP(Table1[[#This Row],[Line Item Text Code]],$U$3:$V$7,2,FALSE) -> Miscellaneous | Q77: =Table1[[#This Row],[Ext. Cost]]-Table1[[#This Row],[Ext. Sell]] -> 25.32 | R77: =VLOOKUP(C77,Bookings!$A$1:$B$33,2,FALSE) -> 13189792 | S77: =IFERROR(VLOOKUP(D77,Bookings!E:F,2,FALSE),0) -> 1874548.9 | T77: =IFERROR(VLOOKUP(Table1[[#This Row],[Order]],Bookings_with_AM_Report!A:L,12,FALSE),"N/A") -> Kimi Katsuyoshi
A78: 83085 | B78: 16 | C78: Owen Cunningham | D78: Sequoia Capital Operations, LLC | E78: MILEAGE | G78: TRV | H78: MISC | I78: Mileage | J78: San Francisco | K78: ASTOR - Astor Ng | L78: 1 | M78: 0 | N78: 12.66 | O78: Kelly Caplan | P78: =VLOOKUP(Table1[[#This Row],[Line Item Text Code]],$U$3:$V$7,2,FALSE) -> Miscellaneous | Q78: =Table1[[#This Row],[Ext. Cost]]-Table1[[#This Row],[Ext. Sell]] -> 12.66 | R78: =VLOOKUP(C78,Bookings!$A$1:$B$33,2,FALSE) -> 13189792 | S78: =IFERROR(VLOOKUP(D78,Bookings!E:F,2,FALSE),0) -> 1874548.9 | T78: =IFERROR(VLOOKUP(Table1[[#This Row],[Order]],Bookings_with_AM_Report!A:L,12,FALSE),"N/A") -> Kimi Katsuyoshi
A79: 83213 | B79: 11 | C79: Olivia Gorfain | D79: HGGC | E79: Labor | F79: Quote Includes • 1 Trip to Site for installers to partially KD Custom workstation and replace power box Optional/ Add-line: Will Call power box from SJ $265.00 • 1 Will Call | G79: FABR | H79: CUST | I79: Customer accomodation. | J79: San Francisco | K79: SERVICE - Service West- San Leandro | L79: 1 | M79: 0 | N79: 1035 | O79: Nicole Lentini | P79: =VLOOKUP(Table1[[#This Row],[Line Item Text Code]],$U$3:$V$7,2,FALSE) -> Customer Accomodation | Q79: =Table1[[#This Row],[Ext. Cost]]-Table1[[#This Row],[Ext. Sell]] -> 1035 | R79: =VLOOKUP(C79,Bookings!$A$1:$B$33,2,FALSE) -> 25594615 | S79: =IFERROR(VLOOKUP(D79,Bookings!E:F,2,FALSE),0) -> 4058.63 | T79: =IFERROR(VLOOKUP(Table1[[#This Row],[Order]],Bookings_with_AM_Report!A:L,12,FALSE),"N/A") -> Emily Stiller
A80: 83213 | B80: 12 | C80: Olivia Gorfain | D80: HGGC | E80: Labor | F80: Optional/ Add-line: Will Call power box from SJ • 1 Will Call | G80: FABR | H80: CUST | I80: Customer accomodation. | J80: San Francisco | K80: SERVICE - Service West- San Leandro | L80: 1 | M80: 0 | N80: 265 | O80: Nicole Lentini | P80: =VLOOKUP(Table1[[#This Row],[Line Item Text Code]],$U$3:$V$7,2,FALSE) -> Customer Accomodation | Q80: =Table1[[#This Row],[Ext. Cost]]-Table1[[#This Row],[Ext. Sell]] -> 265 | R80: =VLOOKUP(C80,Bookings!$A$1:$B$33,2,FALSE) -> 25594615 | S80: =IFERROR(VLOOKUP(D80,Bookings!E:F,2,FALSE),0) -> 4058.63 | T80: =IFERROR(VLOOKUP(Table1[[#This Row],[Order]],Bookings_with_AM_Report!A:L,12,FALSE),"N/A") -> Emily Stiller
A81: 83289 | B81: 12 | C81: Alex Blangeres | D81: Placer County | E81: FREIGHT | F81: Manufacturer Shipping for Custom Mobile Island and Top | G81: PM-TAX | H81: MISC | I81: 3/7/24 PM Time original for Will Call, Order requires added Labor order. MF | J81: Sacramento | K81: KBM-PM - KBM-Hogue Project Management | L81: 1 | M81: 0 | N81: 450 | O81: Marcus Freeman | P81: =VLOOKUP(Table1[[#This Row],[Line Item Text Code]],$U$3:$V$7,2,FALSE) -> Miscellaneous | Q81: =Table1[[#This Row],[Ext. Cost]]-Table1[[#This Row],[Ext. Sell]] -> 450 | R81: =VLOOKUP(C81,Bookings!$A$1:$B$33,2,FALSE) -> 3992449.5 | S81: =IFERROR(VLOOKUP(D81,Bookings!E:F,2,FALSE),0) -> 55745.45 | T81: =IFERROR(VLOOKUP(Table1[[#This Row],[Order]],Bookings_with_AM_Report!A:L,12,FALSE),"N/A") -> N/A
A82: 83464 | B82: 111 | C82: Norma Lopez | D82: Intuit-OR 205 | E82: JPR-MCP- 0128-00 | F82: JPR-MCP-0128-00 THIN TASK - NUT FOR GROMMET | G82: PRO | H82: VEN | I82: Unknown who lost parts/where parts are located | J82: San Jose | K82: JUNIPER - Juniper Design | L82: 2 | M82: 0 | N82: 10 | O82: Julia Torres | P82: =VLOOKUP(Table1[[#This Row],[Line Item Text Code]],$U$3:$V$7,2,FALSE) -> Vendor Caused | Q82: =Table1[[#This Row],[Ext. Cost]]-Table1[[#This Row],[Ext. Sell]] -> 10 | R82: =VLOOKUP(C82,Bookings!$A$1:$B$33,2,FALSE) -> 7904036.3 | S82: =IFERROR(VLOOKUP(D82,Bookings!E:F,2,FALSE),0) -> 6485933.8 | T82: =IFERROR(VLOOKUP(Table1[[#This Row],[Order]],Bookings_with_AM_Report!A:L,12,FALSE),"N/A") -> Carina Collison
A83: 83464 | B83: 112 | C83: Norma Lopez | D83: Intuit-OR 205 | E83: JPR-PWR- 0105 | F83: 24VDC, 2A POWER SUPPLY, 90-264VAC INPUT, 1.5M BLACK BRAIDED CORD, 2.1X5.5MM MALE DC JACK, GLOSSY BLACK COVER JUNIPER LOGO, UL LISTED, INTERCHANGEABLE INTERNATIONAL PINS | G83: PRO | H83: VEN | I83: Unknown who lost parts/where parts are located | J83: San Jose | K83: JUNIPER - Juniper Design | L83: 2 | M83: 0 | N83: 50 | O83: Julia Torres | P83: =VLOOKUP(Table1[[#This Row],[Line Item Text Code]],$U$3:$V$7,2,FALSE) -> Vendor Caused | Q83: =Table1[[#This Row],[Ext. Cost]]-Table1[[#This Row],[Ext. Sell]] -> 50 | R83: =VLOOKUP(C83,Bookings!$A$1:$B$33,2,FALSE) -> 7904036.3 | S83: =IFERROR(VLOOKUP(D83,Bookings!E:F,2,FALSE),0) -> 6485933.8 | T83: =IFERROR(VLOOKUP(Table1[[#This Row],[Order]],Bookings_with_AM_Report!A:L,12,FALSE),"N/A") -> Carina Collison
A84: 83464 | B84: 113 | C84: Norma Lopez | D84: Intuit-OR 205 | E84: CBL-0009 | F84: JUMPER CABLE 2.1MM MALE TO 2.1MM MALE - 18" LENGTH, 22AWG, BLACK | G84: PRO | H84: VEN | I84: Unknown who lost parts/where parts are located | J84: San Jose | K84: JUNIPER - Juniper Design | L84: 2 | M84: 0 | N84: 10 | O84: Julia Torres | P84: =VLOOKUP(Table1[[#This Row],[Line Item Text Code]],$U$3:$V$7,2,FALSE) -> Vendor Caused | Q84: =Table1[[#This Row],[Ext. Cost]]-Table1[[#This Row],[Ext. Sell]] -> 10 | R84: =VLOOKUP(C84,Bookings!$A$1:$B$33,2,FALSE) -> 7904036.3 | S84: =IFERROR(VLOOKUP(D84,Bookings!E:F,2,FALSE),0) -> 6485933.8 | T84: =IFERROR(VLOOKUP(Table1[[#This Row],[Order]],Bookings_with_AM_Report!A:L,12,FALSE),"N/A") -> Carina Collison
A85: 83464 | B85: 114 | C85: Norma Lopez | D85: Intuit-OR 205 | E85: Delivery_011 | F85: UPS Ground | G85: SHIP | H85: VEN | I85: Unknown who lost parts/where parts are located | J85: San Jose | K85: JUNIPER - Juniper Design | L85: 1 | M85: 0 | N85: 25 | O85: Julia Torres | P85: =VLOOKUP(Table1[[#This Row],[Line Item Text Code]],$U$3:$V$7,2,FALSE) -> Vendor Caused | Q85: =Table1[[#This Row],[Ext. Cost]]-Table1[[#This Row],[Ext. Sell]] -> 25 | R85: =VLOOKUP(C85,Bookings!$A$1:$B$33,2,FALSE) -> 7904036.3 | S85: =IFERROR(VLOOKUP(D85,Bookings!E:F,2,FALSE),0) -> 6485933.8 | T85: =IFERROR(VLOOKUP(Table1[[#This Row],[Order]],Bookings_with_AM_Report!A:L,12,FALSE),"N/A") -> Carina Collison
A86: 83464 | B86: 115 | C86: Norma Lopez | D86: Intuit-OR 205 | E86: FABRICATION | F86: Labor for return trip to install (1) missing power for Library table on floor 11 | G86: FABR | H86: VEN | I86: Battery power and cable went missing when we transitioned labor companies | J86: San Jose | K86: OFFICES06 - Office System Installation | L86: 1 | M86: 0 | N86: 225 | O86: Julia Torres | P86: =VLOOKUP(Table1[[#This Row],[Line Item Text Code]],$U$3:$V$7,2,FALSE) -> Vendor Caused | Q86: =Table1[[#This Row],[Ext. Cost]]-Table1[[#This Row],[Ext. Sell]] -> 225 | R86: =VLOOKUP(C86,Bookings!$A$1:$B$33,2,FALSE) -> 7904036.3 | S86: =IFERROR(VLOOKUP(D86,Bookings!E:F,2,FALSE),0) -> 6485933.8 | T86: =IFERROR(VLOOKUP(Table1[[#This Row],[Order]],Bookings_with_AM_Report!A:L,12,FALSE),"N/A") -> Carina Collison
A87: 83563 | B87: 15 | C87: Troy Ocariza | D87: East Side Union High School District | E87: LABOR | F87: SM Non-Union Installation and testing of soundmasking system, during Normal Business Hours. Includes Lift equipment. | G87: FABR | H87: MISC | I87: scissor lift not used | J87: San Jose | K87: MPSLLC - MPSLLC | L87: 1 | M87: 0 | N87: -1500 | O87: Angela Farmer | P87: =VLOOKUP(Table1[[#This Row],[Line Item Text Code]],$U$3:$V$7,2,FALSE) -> Miscellaneous | Q87: =Table1[[#This Row],[Ext. Cost]]-Table1[[#This Row],[Ext. Sell]] -> -1500 | R87: =VLOOKUP(C87,Bookings!$A$1:$B$33,2,FALSE) -> 927982.08 | S87: =IFERROR(VLOOKUP(D87,Bookings!E:F,2,FALSE),0) -> 255103.65 | T87: =IFERROR(VLOOKUP(Table1[[#This Row],[Order]],Bookings_with_AM_Report!A:L,12,FALSE),"N/A") -> Troy Ocariza
A88: 83906 | B88: 31 | C88: Jill Marsh | D88: Charles Schwab | E88: Ariba Fees | F88: January | G88: FEE | H88: VEN | I88: Ariba SAP Fees | J88: San Francisco | K88: ARIBAIN - Ariba, Inc. | L88: 1 | M88: 0 | N88: 107.69 | O88: Nicole Lentini | P88: =VLOOKUP(Table1[[#This Row],[Line Item Text Code]],$U$3:$V$7,2,FALSE) -> Vendor Caused | Q88: =Table1[[#This Row],[Ext. Cost]]-Table1[[#This Row],[Ext. Sell]] -> 107.69 | R88: =VLOOKUP(C88,Bookings!$A$1:$B$33,2,FALSE) -> 6210075.2 | S88: =IFERROR(VLOOKUP(D88,Bookings!E:F,2,FALSE),0) -> 214888.15 | T88: =IFERROR(VLOOKUP(Table1[[#This Row],[Order]],Bookings_with_AM_Report!A:L,12,FALSE),"N/A") -> Paul Razo
A89: 84117 | B89: 52 | C89: Shayle Wallis | D89: Walter's House | E89: RETURN TRIP | F89: CIW - return trip charges | G89: FABR | H89: MISC | I89: Labor | J89: Sacramento | K89: COMMERC04 - Commercial Interiors West, Inc. | L89: 1 | M89: 0 | N89: 480 | O89: Marlene Dyson | P89: =VLOOKUP(Table1[[#This Row],[Line Item Text Code]],$U$3:$V$7,2,FALSE) -> Miscellaneous | Q89: =Table1[[#This Row],[Ext. Cost]]-Table1[[#This Row],[Ext. Sell]] -> 480 | R89: =VLOOKUP(C89,Bookings!$A$1:$B$33,2,FALSE) -> 2269779.3 | S89: =IFERROR(VLOOKUP(D89,Bookings!E:F,2,FALSE),0) -> 89212.4 | T89: =IFERROR(VLOOKUP(Table1[[#This Row],[Order]],Bookings_with_AM_Report!A:L,12,FALSE),"N/A") -> Erika Duarte
A90: 84117 | B90: 53 | C90: Shayle Wallis | D90: Walter's House | E90: DESIGN SERVICES | F90: KBM Hogue Design Services | G90: DSGN | H90: SPEC | I90: Additional Design hours. The sell is on the order 89460 | J90: Sacramento | K90: KBM-DESIGN - KBM-Hogue Design | L90: 43.3333 | M90: 0 | N90: 3250 | O90: Marlene Dyson | P90: =VLOOKUP(Table1[[#This Row],[Line Item Text Code]],$U$3:$V$7,2,FALSE) -> Specification Error | Q90: =Table1[[#This Row],[Ext. Cost]]-Table1[[#This Row],[Ext. Sell]] -> 3250 | R90: =VLOOKUP(C90,Bookings!$A$1:$B$33,2,FALSE) -> 2269779.3 | S90: =IFERROR(VLOOKUP(D90,Bookings!E:F,2,FALSE),0) -> 89212.4 | T90: =IFERROR(VLOOKUP(Table1[[#This Row],[Order]],Bookings_with_AM_Report!A:L,12,FALSE),"N/A") -> Erika Duarte
... A110: 85635 | B110: 11 | C110: Norma Lopez | D110: Intuit-OR 205 | E110: BP-KIT | F110: ELLE HAVEN TABLE BATTERY | G110: PRO | H110: VEN | I110: No one knows or has a clean record of where the batteries are/went | J110: San Jose | K110: HAT - Human Active Technology | L110: 30 | M110: 0 | N110: 4500 | O110: Julia Torres | P110: =VLOOKUP(Table1[[#This Row],[Line Item Text Code]],$U$3:$V$7,2,FALSE) -> Vendor Caused | Q110: =Table1[[#This Row],[Ext. Cost]]-Table1[[#This Row],[Ext. Sell]] -> 4500 | R110: =VLOOKUP(C110,Bookings!$A$1:$B$33,2,FALSE) -> 7904036.3 | S110: =IFERROR(VLOOKUP(D110,Bookings!E:F,2,FALSE),0) -> 6485933.8 | T110: =IFERROR(VLOOKUP(Table1[[#This Row],[Order]],Bookings_with_AM_Report!A:L,12,FALSE),"N/A") -> Carina Collison
A111: 85646 | B111: 11 | C111: Owen Cunningham | D111: Altos Labs, Inc. | E111: Home Depot | G111: PRO | H111: MISC | I111: Home Depot | J111: San Francisco | K111: MARKALV - Mark Alvarez | L111: 1 | M111: 0 | N111: 19.95 | O111: Kelly Caplan | P111: =VLOOKUP(Table1[[#This Row],[Line Item Text Code]],$U$3:$V$7,2,FALSE) -> Miscellaneous | Q111: =Table1[[#This Row],[Ext. Cost]]-Table1[[#This Row],[Ext. Sell]] -> 19.95 | R111: =VLOOKUP(C111,Bookings!$A$1:$B$33,2,FALSE) -> 13189792 | S111: =IFERROR(VLOOKUP(D111,Bookings!E:F,2,FALSE),0) -> 1304608 | T111: =IFERROR(VLOOKUP(Table1[[#This Row],[Order]],Bookings_with_AM_Report!A:L,12,FALSE),"N/A") -> Carina Collison
A112: 85649 | B112: 31 | C112: Owen Cunningham | D112: Altos Labs, Inc. | E112: LABOR | F112: ADDITIONAL LABOR TO COMPLETE/CORRECT INSTALLATION PER AGREED UPON SCOPE BETWEEN KBMH (CARINA) AND ABS (DIANA) | G112: FABR | H112: MISC | I112: Additional labor | J112: San Francisco | K112: ABSFACI - ABS Facility Services, Inc. | L112: 1 | M112: 0 | N112: 4357 | O112: Kelly Caplan | P112: =VLOOKUP(Table1[[#This Row],[Line Item Text Code]],$U$3:$V$7,2,FALSE) -> Miscellaneous | Q112: =Table1[[#This Row],[Ext. Cost]]-Table1[[#This Row],[Ext. Sell]] -> 4357 | R112: =VLOOKUP(C112,Bookings!$A$1:$B$33,2,FALSE) -> 13189792 | S112: =IFERROR(VLOOKUP(D112,Bookings!E:F,2,FALSE),0) -> 1304608 | T112: =IFERROR(VLOOKUP(Table1[[#This Row],[Order]],Bookings_with_AM_Report!A:L,12,FALSE),"N/A") -> Carina Collison
A113: 85649 | B113: 32 | C113: Owen Cunningham | D113: Altos Labs, Inc. | E113: LABOR | F113: SERVICE TO INSPECT ANDREU WORLD PRODUCT FOR DAMAGE | G113: FABR | H113: CUST | I113: 7/7/25: Approved by Matt Denning | J113: San Francisco | K113: ABSFACI - ABS Facility Services, Inc. | L113: 1 | M113: 0 | N113: 229 | O113: Kelly Caplan | P113: =VLOOKUP(Table1[[#This Row],[Line Item Text Code]],$U$3:$V$7,2,FALSE) -> Customer Accomodation | Q113: =Table1[[#This Row],[Ext. Cost]]-Table1[[#This Row],[Ext. Sell]] -> 229 | R113: =VLOOKUP(C113,Bookings!$A$1:$B$33,2,FALSE) -> 13189792 | S113: =IFERROR(VLOOKUP(D113,Bookings!E:F,2,FALSE),0) -> 1304608 | T113: =IFERROR(VLOOKUP(Table1[[#This Row],[Order]],Bookings_with_AM_Report!A:L,12,FALSE),"N/A") -> Carina Collison
A114: 85649 | B114: 33 | C114: Owen Cunningham | D114: Altos Labs, Inc. | E114: LABOR | F114: SERVICE TO INSPECT ANDREU WORLD PRODUCT | G114: FABR | H114: SPEC | I114: AM forgot to have ABS quote inspection of AW product | J114: San Francisco | K114: ABSFACI - ABS Facility Services, Inc. | L114: 1 | M114: 0 | N114: 73 | O114: Kelly Caplan | P114: =VLOOKUP(Table1[[#This Row],[Line Item Text Code]],$U$3:$V$7,2,FALSE) -> Specification Error | Q114: =Table1[[#This Row],[Ext. Cost]]-Table1[[#This Row],[Ext. Sell]] -> 73 | R114: =VLOOKUP(C114,Bookings!$A$1:$B$33,2,FALSE) -> 13189792 | S114: =IFERROR(VLOOKUP(D114,Bookings!E:F,2,FALSE),0) -> 1304608 | T114: =IFERROR(VLOOKUP(Table1[[#This Row],[Order]],Bookings_with_AM_Report!A:L,12,FALSE),"N/A") -> Carina Collison
A115: 85695 | B115: 184 | C115: Simon Sheppard | D115: California Northstate University | E115: LABOR | F115: CIW to return to site at CNU to install the private office and RDI punch items during NBH at standard rate of pay. Quotation # CNURT&PUNCH | G115: FABR | H115: CUST | I115: punch trip | J115: Sacramento | K115: COMMERC04 - Commercial Interiors West, Inc. | L115: 1 | M115: 0 | N115: 374.4 | O115: Marcus Freeman | P115: =VLOOKUP(Table1[[#This Row],[Line Item Text Code]],$U$3:$V$7,2,FALSE) -> Customer Accomodation | Q115: =Table1[[#This Row],[Ext. Cost]]-Table1[[#This Row],[Ext. Sell]] -> 374.4 | R115: =VLOOKUP(C115,Bookings!$A$1:$B$33,2,FALSE) -> 893520.77 | S115: =IFERROR(VLOOKUP(D115,Bookings!E:F,2,FALSE),0) -> 525 | T115: =IFERROR(VLOOKUP(Table1[[#This Row],[Order]],Bookings_with_AM_Report!A:L,12,FALSE),"N/A") -> Farrah Race
A116: 85695 | B116: 185 | C116: Simon Sheppard | D116: California Northstate University | E116: AKYRA | F116: BRC Removal key | G116: PRO | H116: CUST | I116: forgot to order | J116: Sacramento | K116: BRCBUSI - BRC USA | L116: 1 | M116: 0 | N116: 18.29 | O116: Angela Farmer | P116: =VLOOKUP(Table1[[#This Row],[Line Item Text Code]],$U$3:$V$7,2,FALSE) -> Customer Accomodation | Q116: =Table1[[#This Row],[Ext. Cost]]-Table1[[#This Row],[Ext. Sell]] -> 18.29 | R116: =VLOOKUP(C116,Bookings!$A$1:$B$33,2,FALSE) -> 893520.77 | S116: =IFERROR(VLOOKUP(D116,Bookings!E:F,2,FALSE),0) -> 525 | T116: =IFERROR(VLOOKUP(Table1[[#This Row],[Order]],Bookings_with_AM_Report!A:L,12,FALSE),"N/A") -> Farrah Race
A117: 85695 | B117: 186 | C117: Simon Sheppard | D117: California Northstate University | E117: AKY1A-509 silver | F117: BRC Single lock core silver #509 | G117: PRO | H117: CUST | I117: forgot to order | J117: Sacramento | K117: BRCBUSI - BRC USA | L117: 2 | M117: 0 | N117: 36.58 | O117: Angela Farmer | P117: =VLOOKUP(Table1[[#This Row],[Line Item Text Code]],$U$3:$V$7,2,FALSE) -> Customer Accomodation | Q117: =Table1[[#This Row],[Ext. Cost]]-Table1[[#This Row],[Ext. Sell]] -> 36.58 | R117: =VLOOKUP(C117,Bookings!$A$1:$B$33,2,FALSE) -> 893520.77 | S117: =IFERROR(VLOOKUP(D117,Bookings!E:F,2,FALSE),0) -> 525 | T117: =IFERROR(VLOOKUP(Table1[[#This Row],[Order]],Bookings_with_AM_Report!A:L,12,FALSE),"N/A") -> Farrah Race
A118: 85695 | B118: 192 | C118: Simon Sheppard | D118: California Northstate University | E118: 2-357-78330 | G118: SHIP | H118: SHIP | I118: FedEx | J118: Sacramento | K118: FEDERAL - Federal Express | L118: 1 | M118: 0 | N118: 26.63 | O118: Angela Farmer | P118: =VLOOKUP(Table1[[#This Row],[Line Item Text Code]],$U$3:$V$7,2,FALSE) -> Shipping Charges | Q118: =Table1[[#This Row],[Ext. Cost]]-Table1[[#This Row],[Ext. Sell]] -> 26.63 | R118: =VLOOKUP(C118,Bookings!$A$1:$B$33,2,FALSE) -> 893520.77 | S118: =IFERROR(VLOOKUP(D118,Bookings!E:F,2,FALSE),0) -> 525 | T118: =IFERROR(VLOOKUP(Table1[[#This Row],[Order]],Bookings_with_AM_Report!A:L,12,FALSE),"N/A") -> Farrah Race
A119: 85709 | B119: 219 | C119: Alex Blangeres | D119: WelbeHealth, LLC | E119: TRAVEL EXPENSES | G119: TRV | H119: MISC | I119: Travel | J119: Sacramento | K119: RYANMILL - Ryan Millard | L119: 1 | M119: 0 | N119: 66.99 | O119: Angela Farmer | P119: =VLOOKUP(Table1[[#This Row],[Line Item Text Code]],$U$3:$V$7,2,FALSE) -> Miscellaneous | Q119: =Table1[[#This Row],[Ext. Cost]]-Table1[[#This Row],[Ext. Sell]] -> 66.99 | R119: =VLOOKUP(C119,Bookings!$A$1:$B$33,2,FALSE) -> 3992449.5 | S119: =IFERROR(VLOOKUP(D119,Bookings!E:F,2,FALSE),0) -> 339578.9 | T119: =IFERROR(VLOOKUP(Table1[[#This Row],[Order]],Bookings_with_AM_Report!A:L,12,FALSE),"N/A") -> Farrah Race
A120: 85709 | B120: 223 | C120: Alex Blangeres | D120: WelbeHealth, LLC | E120: INSTALL | F120: 4th trip to site to deliver the (5)Recliner chairs | G120: FABR | H120: CUST | I120: additional trips for late arriving product | J120: Sacramento | K120: ABSFACI - ABS Facility Services, Inc. | L120: 1 | M120: 0 | N120: 250 | O120: Angela Farmer | P120: =VLOOKUP(Table1[[#This Row],[Line Item Text Code]],$U$3:$V$7,2,FALSE) -> Customer Accomodation | Q120: =Table1[[#This Row],[Ext. Cost]]-Table1[[#This Row],[Ext. Sell]] -> 250 | R120: =VLOOKUP(C120,Bookings!$A$1:$B$33,2,FALSE) -> 3992449.5 | S120: =IFERROR(VLOOKUP(D120,Bookings!E:F,2,FALSE),0) -> 339578.9 | T120: =IFERROR(VLOOKUP(Table1[[#This Row],[Order]],Bookings_with_AM_Report!A:L,12,FALSE),"N/A") -> Farrah Race
A121: 85709 | B121: 223 | C121: Alex Blangeres | D121: WelbeHealth, LLC | E121: INSTALL | F121: 4th trip to site to deliver the (5)Recliner chairs | G121: FABR | H121: VEN | I121: 11/13/24 Return Trip/Fabrication due to incorrect Panel Sizes - Vendor error. MF | J121: Sacramento | K121: ABSFACI - ABS Facility Services, Inc. | L121: 1 | M121: 0 | N121: 250 | O121: Angela Farmer | P121: =VLOOKUP(Table1[[#This Row],[Line Item Text Code]],$U$3:$V$7,2,FALSE) -> Vendor Caused | Q121: =Table1[[#This Row],[Ext. Cost]]-Table1[[#This Row],[Ext. Sell]] -> 250 | R121: =VLOOKUP(C121,Bookings!$A$1:$B$33,2,FALSE) -> 3992449.5 | S121: =IFERROR(VLOOKUP(D121,Bookings!E:F,2,FALSE),0) -> 339578.9 | T121: =IFERROR(VLOOKUP(Table1[[#This Row],[Order]],Bookings_with_AM_Report!A:L,12,FALSE),"N/A") -> Farrah Race
A122: 85709 | B122: 224 | C122: Alex Blangeres | D122: WelbeHealth, LLC | E122: INSTALL | F122: Receive, deliver and install the following back ordered product to Welbe in San Bernardino, regular business hours: (1) recliner | G122: FABR | H122: VEN | I122: 11/13/24 Return Trip/Fabrication due to incorrect Panel Sizes - Vendor error. MF | J122: Sacramento | K122: ABSFACI - ABS Facility Services, Inc. | L122: 1 | M122: 0 | N122: 200 | O122: Angela Farmer | P122: =VLOOKUP(Table1[[#This Row],[Line Item Text Code]],$U$3:$V$7,2,FALSE) -> Vendor Caused | Q122: =Table1[[#This Row],[Ext. Cost]]-Table1[[#This Row],[Ext. Sell]] -> 200 | R122: =VLOOKUP(C122,Bookings!$A$1:$B$33,2,FALSE) -> 3992449.5 | S122: =IFERROR(VLOOKUP(D122,Bookings!E:F,2,FALSE),0) -> 339578.9 | T122: =IFERROR(VLOOKUP(Table1[[#This Row],[Order]],Bookings_with_AM_Report!A:L,12,FALSE),"N/A") -> Farrah Race
A123: 85709 | B123: 224 | C123: Alex Blangeres | D123: WelbeHealth, LLC | E123: INSTALL | F123: Receive, deliver and install the following back ordered product to Welbe in San Bernardino, regular business hours: (1) recliner | G123: FABR | H123: CUST | I123: additional trips for late arriving product | J123: Sacramento | K123: ABSFACI - ABS Facility Services, Inc. | L123: 1 | M123: 0 | N123: 200 | O123: Angela Farmer | P123: =VLOOKUP(Table1[[#This Row],[Line Item Text Code]],$U$3:$V$7,2,FALSE) -> Customer Accomodation | Q123: =Table1[[#This Row],[Ext. Cost]]-Table1[[#This Row],[Ext. Sell]] -> 200 | R123: =VLOOKUP(C123,Bookings!$A$1:$B$33,2,FALSE) -> 3992449.5 | S123: =IFERROR(VLOOKUP(D123,Bookings!E:F,2,FALSE),0) -> 339578.9 | T123: =IFERROR(VLOOKUP(Table1[[#This Row],[Order]],Bookings_with_AM_Report!A:L,12,FALSE),"N/A") -> Farrah Race
A124: 85889 | B124: 97 | C124: Owen Cunningham | D124: Meritech Capital | E124: XSAB180 | F124: **ACCESS DOOR ONLY** Odyssey Table Base for 48"-60"D x 180"W Rectangle Top Paint : R – Black | G124: PRO | H124: CUST | I124: . | J124: San Francisco | K124: ENW - Enwork | L124: 1 | M124: 0 | N124: 224.4 | O124: Kelly Caplan | P124: =VLOOKUP(Table1[[#This Row],[Line Item Text Code]],$U$3:$V$7,2,FALSE) -> Customer Accomodation | Q124: =Table1[[#This Row],[Ext. Cost]]-Table1[[#This Row],[Ext. Sell]] -> 224.4 | R124: =VLOOKUP(C124,Bookings!$A$1:$B$33,2,FALSE) -> 13189792 | S124: =IFERROR(VLOOKUP(D124,Bookings!E:F,2,FALSE),0) -> 44311 | T124: =IFERROR(VLOOKUP(Table1[[#This Row],[Order]],Bookings_with_AM_Report!A:L,12,FALSE),"N/A") -> Frances Kim
A125: 85889 | B125: 98 | C125: Owen Cunningham | D125: Meritech Capital | E125: CUSTOMS CHARGES | F125: CUSTOMS CHARGES | G125: TAR | H125: SHIP | I125: . | J125: San Francisco | K125: LIVINGS - Livingston International | L125: 1 | M125: 0 | N125: 409.4 | O125: Kelly Caplan | P125: =VLOOKUP(Table1[[#This Row],[Line Item Text Code]],$U$3:$V$7,2,FALSE) -> Shipping Charges | Q125: =Table1[[#This Row],[Ext. Cost]]-Table1[[#This Row],[Ext. Sell]] -> 409.4 | R125: =VLOOKUP(C125,Bookings!$A$1:$B$33,2,FALSE) -> 13189792 | S125: =IFERROR(VLOOKUP(D125,Bookings!E:F,2,FALSE),0) -> 44311 | T125: =IFERROR(VLOOKUP(Table1[[#This Row],[Order]],Bookings_with_AM_Report!A:L,12,FALSE),"N/A") -> Frances Kim
A126: 85901 | B126: 10 | C126: Simon Sheppard | D126: Tri Pointe Homes Holdings, Inc | E126: DESIGN | F126: Design, Specification, Drawings | G126: DSGN | H126: MISC | I126: True-Up | J126: Sacramento | K126: KBM-DESIGN - KBM-Hogue Design | L126: 1 | M126: 0 | N126: 1575 | O126: Marcus Freeman | P126: =VLOOKUP(Table1[[#This Row],[Line Item Text Code]],$U$3:$V$7,2,FALSE) -> Miscellaneous | Q126: =Table1[[#This Row],[Ext. Cost]]-Table1[[#This Row],[Ext. Sell]] -> 1575 | R126: =VLOOKUP(C126,Bookings!$A$1:$B$33,2,FALSE) -> 893520.77 | S126: =IFERROR(VLOOKUP(D126,Bookings!E:F,2,FALSE),0) -> 121573.87 | T126: =IFERROR(VLOOKUP(Table1[[#This Row],[Order]],Bookings_with_AM_Report!A:L,12,FALSE),"N/A") -> N/A
A127: 85940 | B127: 16 | C127: Shayle Wallis | D127: Sacramento Area Council of Governments | E127: LABOR | F127: Labor for punch trips made to SACOG on 12/20 and 3/14 | G127: FABR | H127: CUST | I127: punch trips trying to bill back knoll | J127: Sacramento | K127: COMMERC04 - Commercial Interiors West, Inc. | L127: 1 | M127: 0 | N127: 617.5 | O127: Marcus Freeman | P127: =VLOOKUP(Table1[[#This Row],[Line Item Text Code]],$U$3:$V$7,2,FALSE) -> Customer Accomodation | Q127: =Table1[[#This Row],[Ext. Cost]]-Table1[[#This Row],[Ext. Sell]] -> 617.5 | R127: =VLOOKUP(C127,Bookings!$A$1:$B$33,2,FALSE) -> 2269779.3 | S127: =IFERROR(VLOOKUP(D127,Bookings!E:F,2,FALSE),0) -> 4090.84 | T127: =IFERROR(VLOOKUP(Table1[[#This Row],[Order]],Bookings_with_AM_Report!A:L,12,FALSE),"N/A") -> Farrah Race
A128: 86032 | B128: 588 | C128: Simon Sheppard | D128: Visions in Education | E128: A1354.36G--LU | F128: *Base Pwr Adapter,W/Covers 4-Circ W/Rcp & Com Pt 36W OPTION: LU:*soft white | G128: PRO | H128: CUST | I128: forgot to order on original order | J128: Sacramento | K128: HMI - Herman Miller | L128: 1 | M128: 0 | N128: 92.5 | O128: Angela Farmer | P128: =VLOOKUP(Table1[[#This Row],[Line Item Text Code]],$U$3:$V$7,2,FALSE) -> Customer Accomodation | Q128: =Table1[[#This Row],[Ext. Cost]]-Table1[[#This Row],[Ext. Sell]] -> 92.5 | R128: =VLOOKUP(C128,Bookings!$A$1:$B$33,2,FALSE) -> 893520.77 | S128: =IFERROR(VLOOKUP(D128,Bookings!E:F,2,FALSE),0) -> 2979.98 | T128: =IFERROR(VLOOKUP(Table1[[#This Row],[Order]],Bookings_with_AM_Report!A:L,12,FALSE),"N/A") -> Farrah Race
A129: 86032 | B129: 589 | C129: Simon Sheppard | D129: Visions in Education | E129: A1120.6724N--LU-LU-3DE-03-3DE-03 | F129: *Panel,Fabric Npwr 67H 24W OPTION: LU:*soft white OPTION: LU:*soft white OPTION: 3DE:*dex-Pr Cat 1 OPTION: 03:*dex stone OPTION: 3DE:*dex-Pr Cat 1 OPTION: 03:*dex stone | G129: PRO | H129: CUST | I129: need to correct issue on site | J129: Sacramento | K129: HMI - Herman Miller | L129: 1 | M129: 0 | N129: 209.5 | O129: Angela Farmer | P129: =VLOOKUP(Table1[[#This Row],[Line Item Text Code]],$U$3:$V$7,2,FALSE) -> Customer Accomodation | Q129: =Table1[[#This Row],[Ext. Cost]]-Table1[[#This Row],[Ext. Sell]] -> 209.5 | R129: =VLOOKUP(C129,Bookings!$A$1:$B$33,2,FALSE) -> 893520.77 | S129: =IFERROR(VLOOKUP(D129,Bookings!E:F,2,FALSE),0) -> 2979.98 | T129: =IFERROR(VLOOKUP(Table1[[#This Row],[Order]],Bookings_with_AM_Report!A:L,12,FALSE),"N/A") -> Farrah Race
A130: 86032 | B130: 590 | C130: Simon Sheppard | D130: Visions in Education | E130: AO215.62 | F130: *Draw Rod 62H | G130: PRO | H130: CUST | I130: need to correct issue on site | J130: Sacramento | K130: HMI - Herman Miller | L130: 1 | M130: 0 | N130: 11.75 | O130: Angela Farmer | P130: =VLOOKUP(Table1[[#This Row],[Line Item Text Code]],$U$3:$V$7,2,FALSE) -> Customer Accomodation | Q130: =Table1[[#This Row],[Ext. Cost]]-Table1[[#This Row],[Ext. Sell]] -> 11.75 | R130: =VLOOKUP(C130,Bookings!$A$1:$B$33,2,FALSE) -> 893520.77 | S130: =IFERROR(VLOOKUP(D130,Bookings!E:F,2,FALSE),0) -> 2979.98 | T130: =IFERROR(VLOOKUP(Table1[[#This Row],[Order]],Bookings_with_AM_Report!A:L,12,FALSE),"N/A") -> Farrah Race
A131: 86032 | B131: 591 | C131: Simon Sheppard | D131: Visions in Education | E131: FABRICATION | F131: Scope of Work Modify the following Herman Miller AO2 furniture: • 2-each 39/30 AO2 panels , to 39/24” Wide • 2-each 24/60 work surfaces to 24/54” Wide F.O.B. our shop Will call-By CIW | G131: FABR | H131: SPEC | I131: correct spec error cost | J131: Sacramento | K131: CUSTOMT - Custom Transitions, Inc. | L131: 1 | M131: 0 | N131: 320 | O131: Angela Farmer | P131: =VLOOKUP(Table1[[#This Row],[Line Item Text Code]],$U$3:$V$7,2,FALSE) -> Specification Error | Q131: =Table1[[#This Row],[Ext. Cost]]-Table1[[#This Row],[Ext. Sell]] -> 320 | R131: =VLOOKUP(C131,Bookings!$A$1:$B$33,2,FALSE) -> 893520.77 | S131: =IFERROR(VLOOKUP(D131,Bookings!E:F,2,FALSE),0) -> 2979.98 | T131: =IFERROR(VLOOKUP(Table1[[#This Row],[Order]],Bookings_with_AM_Report!A:L,12,FALSE),"N/A") -> Farrah Race
... A163: 86753 | B163: 142 | C163: Troy Ocariza | D163: Swinerton Builders (GC) | E163: HLKRTB115 | F163: Universal Textured Finish Lacquer Paint, (2) 1 oz Bottles, Slate / Medium Grey, 24-Response | G163: PRO | H163: CUST | I163: touch up for punch | J163: Sacramento | K163: KNO - Knoll, Inc. | L163: 1 | M163: -19.13 | N163: 0 | O163: Angela Farmer | P163: =VLOOKUP(Table1[[#This Row],[Line Item Text Code]],$U$3:$V$7,2,FALSE) -> Customer Accomodation | Q163: =Table1[[#This Row],[Ext. Cost]]-Table1[[#This Row],[Ext. Sell]] -> 19.13 | R163: =VLOOKUP(C163,Bookings!$A$1:$B$33,2,FALSE) -> 927982.08 | S163: =IFERROR(VLOOKUP(D163,Bookings!E:F,2,FALSE),0) -> 17655.11 | T163: =IFERROR(VLOOKUP(Table1[[#This Row],[Order]],Bookings_with_AM_Report!A:L,12,FALSE),"N/A") -> Troy Ocariza
A164: 86822 | B164: 17 | C164: Norma Lopez | D164: Intuit-OR 205 | E164: travel | G164: TRV | H164: MISC | I164: Travel | J164: San Jose | K164: OLIVERC1 - Oliver Collado | L164: 1 | M164: 0 | N164: 117.24 | O164: Julia Torres | P164: =VLOOKUP(Table1[[#This Row],[Line Item Text Code]],$U$3:$V$7,2,FALSE) -> Miscellaneous | Q164: =Table1[[#This Row],[Ext. Cost]]-Table1[[#This Row],[Ext. Sell]] -> 117.24 | R164: =VLOOKUP(C164,Bookings!$A$1:$B$33,2,FALSE) -> 7904036.3 | S164: =IFERROR(VLOOKUP(D164,Bookings!E:F,2,FALSE),0) -> 6485933.8 | T164: =IFERROR(VLOOKUP(Table1[[#This Row],[Order]],Bookings_with_AM_Report!A:L,12,FALSE),"N/A") -> Norma Lopez
A165: 86822 | B165: 18 | C165: Norma Lopez | D165: Intuit-OR 205 | E165: travel | G165: TRV | H165: MISC | I165: Travel | J165: San Jose | K165: OLIVERC1 - Oliver Collado | L165: 1 | M165: 0 | N165: 92.52 | O165: Julia Torres | P165: =VLOOKUP(Table1[[#This Row],[Line Item Text Code]],$U$3:$V$7,2,FALSE) -> Miscellaneous | Q165: =Table1[[#This Row],[Ext. Cost]]-Table1[[#This Row],[Ext. Sell]] -> 92.52 | R165: =VLOOKUP(C165,Bookings!$A$1:$B$33,2,FALSE) -> 7904036.3 | S165: =IFERROR(VLOOKUP(D165,Bookings!E:F,2,FALSE),0) -> 6485933.8 | T165: =IFERROR(VLOOKUP(Table1[[#This Row],[Order]],Bookings_with_AM_Report!A:L,12,FALSE),"N/A") -> Norma Lopez
A166: 86822 | B166: 19 | C166: Norma Lopez | D166: Intuit-OR 205 | E166: PARKING | G166: TRV | H166: MISC | I166: Parking | J166: San Jose | K166: OLIVERC1 - Oliver Collado | L166: 1 | M166: 0 | N166: 70 | O166: Julia Torres | P166: =VLOOKUP(Table1[[#This Row],[Line Item Text Code]],$U$3:$V$7,2,FALSE) -> Miscellaneous | Q166: =Table1[[#This Row],[Ext. Cost]]-Table1[[#This Row],[Ext. Sell]] -> 70 | R166: =VLOOKUP(C166,Bookings!$A$1:$B$33,2,FALSE) -> 7904036.3 | S166: =IFERROR(VLOOKUP(D166,Bookings!E:F,2,FALSE),0) -> 6485933.8 | T166: =IFERROR(VLOOKUP(Table1[[#This Row],[Order]],Bookings_with_AM_Report!A:L,12,FALSE),"N/A") -> Norma Lopez
A167: 86822 | B167: 20 | C167: Norma Lopez | D167: Intuit-OR 205 | E167: travel | G167: TRV | H167: MISC | I167: Travel | J167: San Jose | K167: OLIVERC1 - Oliver Collado | L167: 1 | M167: 0 | N167: 119.64 | O167: Julia Torres | P167: =VLOOKUP(Table1[[#This Row],[Line Item Text Code]],$U$3:$V$7,2,FALSE) -> Miscellaneous | Q167: =Table1[[#This Row],[Ext. Cost]]-Table1[[#This Row],[Ext. Sell]] -> 119.64 | R167: =VLOOKUP(C167,Bookings!$A$1:$B$33,2,FALSE) -> 7904036.3 | S167: =IFERROR(VLOOKUP(D167,Bookings!E:F,2,FALSE),0) -> 6485933.8 | T167: =IFERROR(VLOOKUP(Table1[[#This Row],[Order]],Bookings_with_AM_Report!A:L,12,FALSE),"N/A") -> Norma Lopez
A168: 86822 | B168: 21 | C168: Norma Lopez | D168: Intuit-OR 205 | E168: PARKING | G168: TRV | H168: MISC | I168: Parking | J168: San Jose | K168: CONNIE - Connie Le | L168: 1 | M168: 0 | N168: 25 | O168: Julia Torres | P168: =VLOOKUP(Table1[[#This Row],[Line Item Text Code]],$U$3:$V$7,2,FALSE) -> Miscellaneous | Q168: =Table1[[#This Row],[Ext. Cost]]-Table1[[#This Row],[Ext. Sell]] -> 25 | R168: =VLOOKUP(C168,Bookings!$A$1:$B$33,2,FALSE) -> 7904036.3 | S168: =IFERROR(VLOOKUP(D168,Bookings!E:F,2,FALSE),0) -> 6485933.8 | T168: =IFERROR(VLOOKUP(Table1[[#This Row],[Order]],Bookings_with_AM_Report!A:L,12,FALSE),"N/A") -> Norma Lopez
A169: 86822 | B169: 22 | C169: Norma Lopez | D169: Intuit-OR 205 | E169: PARKING | G169: TRV | H169: MISC | I169: Parking | J169: San Jose | K169: OLIVERC1 - Oliver Collado | L169: 1 | M169: 0 | N169: 70 | O169: Julia Torres | P169: =VLOOKUP(Table1[[#This Row],[Line Item Text Code]],$U$3:$V$7,2,FALSE) -> Miscellaneous | Q169: =Table1[[#This Row],[Ext. Cost]]-Table1[[#This Row],[Ext. Sell]] -> 70 | R169: =VLOOKUP(C169,Bookings!$A$1:$B$33,2,FALSE) -> 7904036.3 | S169: =IFERROR(VLOOKUP(D169,Bookings!E:F,2,FALSE),0) -> 6485933.8 | T169: =IFERROR(VLOOKUP(Table1[[#This Row],[Order]],Bookings_with_AM_Report!A:L,12,FALSE),"N/A") -> Norma Lopez
A170: 86840 | B170: 63 | C170: Owen Cunningham | D170: Palmetto Solar, LLC | E170: PRODUCT | F170: Credit for Palmetto to accept reception desk as is. | G170: PRO | H170: VEN | I170: Credit to client for $2000 Owen arranged to receive credit for $1000 from CW. See 91506. | J170: San Francisco | K170: CREATIV04 - Creative Wood Products | L170: 1 | M170: -2000 | N170: 0 | O170: Kelly Caplan | P170: =VLOOKUP(Table1[[#This Row],[Line Item Text Code]],$U$3:$V$7,2,FALSE) -> Vendor Caused | Q170: =Table1[[#This Row],[Ext. Cost]]-Table1[[#This Row],[Ext. Sell]] -> 2000 | R170: =VLOOKUP(C170,Bookings!$A$1:$B$33,2,FALSE) -> 13189792 | S170: =IFERROR(VLOOKUP(D170,Bookings!E:F,2,FALSE),0) -> 86409 | T170: =IFERROR(VLOOKUP(Table1[[#This Row],[Order]],Bookings_with_AM_Report!A:L,12,FALSE),"N/A") -> Frances Kim
A171: 86840 | B171: 64 | C171: Owen Cunningham | D171: Palmetto Solar, LLC | E171: 8-776-52402 | G171: SHIP | H171: SHIP | I171: FedEx | J171: San Francisco | K171: FEDERAL - Federal Express | L171: 1 | M171: 0 | N171: 53.76 | O171: Kelly Caplan | P171: =VLOOKUP(Table1[[#This Row],[Line Item Text Code]],$U$3:$V$7,2,FALSE) -> Shipping Charges | Q171: =Table1[[#This Row],[Ext. Cost]]-Table1[[#This Row],[Ext. Sell]] -> 53.76 | R171: =VLOOKUP(C171,Bookings!$A$1:$B$33,2,FALSE) -> 13189792 | S171: =IFERROR(VLOOKUP(D171,Bookings!E:F,2,FALSE),0) -> 86409 | T171: =IFERROR(VLOOKUP(Table1[[#This Row],[Order]],Bookings_with_AM_Report!A:L,12,FALSE),"N/A") -> Frances Kim
A172: 86914 | B172: 21 | C172: Jenni Lombardi | D172: Wilson Sonsini Goodrich & Rosati | E172: 8-819-38519 | G172: SHIP | H172: MISC | I172: FedEx | J172: San Jose | K172: FEDERAL - Federal Express | L172: 1 | M172: 0 | N172: 10 | O172: Haley Berger | P172: =VLOOKUP(Table1[[#This Row],[Line Item Text Code]],$U$3:$V$7,2,FALSE) -> Miscellaneous | Q172: =Table1[[#This Row],[Ext. Cost]]-Table1[[#This Row],[Ext. Sell]] -> 10 | R172: =VLOOKUP(C172,Bookings!$A$1:$B$33,2,FALSE) -> 3917134.9 | S172: =IFERROR(VLOOKUP(D172,Bookings!E:F,2,FALSE),0) -> 3461933.9 | T172: =IFERROR(VLOOKUP(Table1[[#This Row],[Order]],Bookings_with_AM_Report!A:L,12,FALSE),"N/A") -> Jenni Lombardi
A173: 86917 | B173: 10 | C173: Norma Lopez | D173: Intuit-OR 205 | E173: HOME DEPOT | G173: PRO | H173: MISC | I173: Hardware | J173: San Jose | K173: JOHNLIC - John Liclican | L173: 1 | M173: 0 | N173: 68.17 | O173: Julia Torres | P173: =VLOOKUP(Table1[[#This Row],[Line Item Text Code]],$U$3:$V$7,2,FALSE) -> Miscellaneous | Q173: =Table1[[#This Row],[Ext. Cost]]-Table1[[#This Row],[Ext. Sell]] -> 68.17 | R173: =VLOOKUP(C173,Bookings!$A$1:$B$33,2,FALSE) -> 7904036.3 | S173: =IFERROR(VLOOKUP(D173,Bookings!E:F,2,FALSE),0) -> 6485933.8 | T173: =IFERROR(VLOOKUP(Table1[[#This Row],[Order]],Bookings_with_AM_Report!A:L,12,FALSE),"N/A") -> Norma Lopez
A174: 87025 | B174: 31 | C174: Jill Marsh | D174: Stanford School of Humanities and Sciences | E174: C-EMW-84----- | F174: ARISE MARKERWALL OPTION: :1/4" THICK w/PC TRIM 8'x4' JOINED ON OPTION: :JOB W/ SPLINE JOINTS TO MAKE A OPTION: :6'H X 12'W CHALKBOARD RUN | G174: PRO | H174: SPEC | I174: originally not spec'd correctly | J174: San Francisco | K174: CLARIDG - Claridge Products & Equipment, Inc. | L174: 3 | M174: 0 | N174: 1222.98 | O174: Julia Torres | P174: =VLOOKUP(Table1[[#This Row],[Line Item Text Code]],$U$3:$V$7,2,FALSE) -> Specification Error | Q174: =Table1[[#This Row],[Ext. Cost]]-Table1[[#This Row],[Ext. Sell]] -> 1222.98 | R174: =VLOOKUP(C174,Bookings!$A$1:$B$33,2,FALSE) -> 6210075.2 | S174: =IFERROR(VLOOKUP(D174,Bookings!E:F,2,FALSE),0) -> -1032.98 | T174: =IFERROR(VLOOKUP(Table1[[#This Row],[Order]],Bookings_with_AM_Report!A:L,12,FALSE),"N/A") -> Patty Medina
A175: 87025 | B175: 32 | C175: Jill Marsh | D175: Stanford School of Humanities and Sciences | E175: SHIPPING | F175: Shipping | G175: PRO | H175: SHIP | I175: shipping | J175: San Francisco | K175: CLARIDG - Claridge Products & Equipment, Inc. | L175: 1 | M175: 0 | N175: 250 | O175: Julia Torres | P175: =VLOOKUP(Table1[[#This Row],[Line Item Text Code]],$U$3:$V$7,2,FALSE) -> Shipping Charges | Q175: =Table1[[#This Row],[Ext. Cost]]-Table1[[#This Row],[Ext. Sell]] -> 250 | R175: =VLOOKUP(C175,Bookings!$A$1:$B$33,2,FALSE) -> 6210075.2 | S175: =IFERROR(VLOOKUP(D175,Bookings!E:F,2,FALSE),0) -> -1032.98 | T175: =IFERROR(VLOOKUP(Table1[[#This Row],[Order]],Bookings_with_AM_Report!A:L,12,FALSE),"N/A") -> Patty Medina
A176: 87143 | B176: 101 | C176: Owen Cunningham | D176: Sequoia Capital Operations, LLC | E176: MIILEAGE | G176: TRV | H176: MISC | I176: Mileage | J176: San Francisco | K176: ASTOR - Astor Ng | L176: 1 | M176: 0 | N176: 31.66 | O176: Kelly Caplan | P176: =VLOOKUP(Table1[[#This Row],[Line Item Text Code]],$U$3:$V$7,2,FALSE) -> Miscellaneous | Q176: =Table1[[#This Row],[Ext. Cost]]-Table1[[#This Row],[Ext. Sell]] -> 31.66 | R176: =VLOOKUP(C176,Bookings!$A$1:$B$33,2,FALSE) -> 13189792 | S176: =IFERROR(VLOOKUP(D176,Bookings!E:F,2,FALSE),0) -> 1874548.9 | T176: =IFERROR(VLOOKUP(Table1[[#This Row],[Order]],Bookings_with_AM_Report!A:L,12,FALSE),"N/A") -> Kimi Katsuyoshi
A177: 87143 | B177: 102 | C177: Owen Cunningham | D177: Sequoia Capital Operations, LLC | E177: MIILEAGE | G177: TRV | H177: MISC | I177: Mileage | J177: San Francisco | K177: ASTOR - Astor Ng | L177: 1 | M177: 0 | N177: 12.66 | O177: Kelly Caplan | P177: =VLOOKUP(Table1[[#This Row],[Line Item Text Code]],$U$3:$V$7,2,FALSE) -> Miscellaneous | Q177: =Table1[[#This Row],[Ext. Cost]]-Table1[[#This Row],[Ext. Sell]] -> 12.66 | R177: =VLOOKUP(C177,Bookings!$A$1:$B$33,2,FALSE) -> 13189792 | S177: =IFERROR(VLOOKUP(D177,Bookings!E:F,2,FALSE),0) -> 1874548.9 | T177: =IFERROR(VLOOKUP(Table1[[#This Row],[Order]],Bookings_with_AM_Report!A:L,12,FALSE),"N/A") -> Kimi Katsuyoshi
A178: 87143 | B178: 105 | C178: Owen Cunningham | D178: Sequoia Capital Operations, LLC | E178: AMAZON PRODUCT | G178: PRO | H178: MISC | I178: Amazon product | J178: San Francisco | K178: KIMIKOK - Kimiko Katsuyoshi | L178: 1 | M178: 0 | N178: 92.16 | O178: Kelly Caplan | P178: =VLOOKUP(Table1[[#This Row],[Line Item Text Code]],$U$3:$V$7,2,FALSE) -> Miscellaneous | Q178: =Table1[[#This Row],[Ext. Cost]]-Table1[[#This Row],[Ext. Sell]] -> 92.16 | R178: =VLOOKUP(C178,Bookings!$A$1:$B$33,2,FALSE) -> 13189792 | S178: =IFERROR(VLOOKUP(D178,Bookings!E:F,2,FALSE),0) -> 1874548.9 | T178: =IFERROR(VLOOKUP(Table1[[#This Row],[Order]],Bookings_with_AM_Report!A:L,12,FALSE),"N/A") -> Kimi Katsuyoshi
A179: 87152 | B179: 18 | C179: Krissa Collins | D179: Mather VA Integrated Patient Modular Casework | E179: HOME DEPOT | G179: PRO | H179: MISC | I179: Home Depot | J179: Sacramento | K179: RYANMILL - Ryan Millard | L179: 1 | M179: 0 | N179: 26.03 | O179: Angela Farmer | P179: =VLOOKUP(Table1[[#This Row],[Line Item Text Code]],$U$3:$V$7,2,FALSE) -> Miscellaneous | Q179: =Table1[[#This Row],[Ext. Cost]]-Table1[[#This Row],[Ext. Sell]] -> 26.03 | R179: =VLOOKUP(C179,Bookings!$A$1:$B$33,2,FALSE) -> 105326.69 | S179: =IFERROR(VLOOKUP(D179,Bookings!E:F,2,FALSE),0) -> 0 | T179: =IFERROR(VLOOKUP(Table1[[#This Row],[Order]],Bookings_with_AM_Report!A:L,12,FALSE),"N/A") -> Farrah Race
A180: 87187 | B180: 288 | C180: Owen Cunningham | D180: Digital Realty Trust | E180: LABOR | F180: Return Trip to site to install Overhead Sliding Door Plastic Rails shorted by manufacturer in Office 1521 | G180: FABR | H180: VEN | I180: Vendor caused/billed back | J180: San Francisco | K180: TURNKEY01 - Turnkey Project Services- TX | L180: 1 | M180: 0 | N180: 345 | O180: Kelly Caplan | P180: =VLOOKUP(Table1[[#This Row],[Line Item Text Code]],$U$3:$V$7,2,FALSE) -> Vendor Caused | Q180: =Table1[[#This Row],[Ext. Cost]]-Table1[[#This Row],[Ext. Sell]] -> 345 | R180: =VLOOKUP(C180,Bookings!$A$1:$B$33,2,FALSE) -> 13189792 | S180: =IFERROR(VLOOKUP(D180,Bookings!E:F,2,FALSE),0) -> 366142.83 | T180: =IFERROR(VLOOKUP(Table1[[#This Row],[Order]],Bookings_with_AM_Report!A:L,12,FALSE),"N/A") -> Erika Duarte
A181: 87187 | B181: 289 | C181: Owen Cunningham | D181: Digital Realty Trust | E181: LABOR | F181: For Office 1605 - Cut down 24x60 surface to 24x54 | G181: FABR | H181: SPEC | I181: Per Erika, the cut had to be done for the desk to be installed/spec error. | J181: San Francisco | K181: TURNKEY01 - Turnkey Project Services- TX | L181: 1 | M181: 0 | N181: 60 | O181: Kelly Caplan | P181: =VLOOKUP(Table1[[#This Row],[Line Item Text Code]],$U$3:$V$7,2,FALSE) -> Specification Error | Q181: =Table1[[#This Row],[Ext. Cost]]-Table1[[#This Row],[Ext. Sell]] -> 60 | R181: =VLOOKUP(C181,Bookings!$A$1:$B$33,2,FALSE) -> 13189792 | S181: =IFERROR(VLOOKUP(D181,Bookings!E:F,2,FALSE),0) -> 366142.83 | T181: =IFERROR(VLOOKUP(Table1[[#This Row],[Order]],Bookings_with_AM_Report!A:L,12,FALSE),"N/A") -> Erika Duarte
A182: 87224 | B182: 20 | C182: Kimi Katsuyoshi | D182: Berkeley Research Group, LLC | E182: WAREHOUSE STORAGE | F182: Warehouse Storage - April (4/11-5/11/25) | G182: STORE | H182: CUST | I182: Job cost for client prior to install | J182: San Francisco | K182: CIMINOS - Cimino's Office Systems | L182: 1 | M182: 0 | N182: 28.8 | O182: Kelly Caplan | P182: =VLOOKUP(Table1[[#This Row],[Line Item Text Code]],$U$3:$V$7,2,FALSE) -> Customer Accomodation | Q182: =Table1[[#This Row],[Ext. Cost]]-Table1[[#This Row],[Ext. Sell]] -> 28.8 | R182: =VLOOKUP(C182,Bookings!$A$1:$B$33,2,FALSE) -> 17992.6 | S182: =IFERROR(VLOOKUP(D182,Bookings!E:F,2,FALSE),0) -> 9499.6 | T182: =IFERROR(VLOOKUP(Table1[[#This Row],[Order]],Bookings_with_AM_Report!A:L,12,FALSE),"N/A") -> Frances Kim
A183: 87247 | B183: 123 | C183: Lela Huenergardt | D183: Santa Clara County Library District | E183: FT181.2236P--91-91 | F183: +Upper Tile,22" h,36" w,painted OPTION: 91:+white (CP) OPTION: 91:+white (CP) | G183: PRO | H183: SPEC | I183: This is due to a design error. Didn't specify the correct amount. | J183: San Jose | K183: HMI - Herman Miller | L183: 2 | M183: 0 | N183: 63.64 | O183: Marlene Dyson | P183: =VLOOKUP(Table1[[#This Row],[Line Item Text Code]],$U$3:$V$7,2,FALSE) -> Specification Error | Q183: =Table1[[#This Row],[Ext. Cost]]-Table1[[#This Row],[Ext. Sell]] -> 63.64 | R183: =VLOOKUP(C183,Bookings!$A$1:$B$33,2,FALSE) -> 3879926.5 | S183: =IFERROR(VLOOKUP(D183,Bookings!E:F,2,FALSE),0) -> 23189.56 | T183: =IFERROR(VLOOKUP(Table1[[#This Row],[Order]],Bookings_with_AM_Report!A:L,12,FALSE),"N/A") -> Marena Brown
A184: 87247 | B184: 129 | C184: Lela Huenergardt | D184: Santa Clara County Library District | E184: B3164244 | F184: Global Industrial 5 Shelf, Standard Duty Boltless Shelving, Starter, 96"W x 24"D x 96"H,Wood Deck | G184: PRO | H184: SPEC | I184: little spec error and a little client error because the room was not the size provided. ordering at cost only to get the install completed. | J184: San Jose | K184: GLOBALE - Global Industrial | L184: 1 | M184: 0 | N184: 482.67 | O184: Marlene Dyson | P184: =VLOOKUP(Table1[[#This Row],[Line Item Text Code]],$U$3:$V$7,2,FALSE) -> Specification Error | Q184: =Table1[[#This Row],[Ext. Cost]]-Table1[[#This Row],[Ext. Sell]] -> 482.67 | R184: =VLOOKUP(C184,Bookings!$A$1:$B$33,2,FALSE) -> 3879926.5 | S184: =IFERROR(VLOOKUP(D184,Bookings!E:F,2,FALSE),0) -> 23189.56 | T184: =IFERROR(VLOOKUP(Table1[[#This Row],[Order]],Bookings_with_AM_Report!A:L,12,FALSE),"N/A") -> Marena Brown
A185: 87247 | B185: 130 | C185: Lela Huenergardt | D185: Santa Clara County Library District | E185: FREIGHT | F185: Shipping & Handling | G185: SHIP | H185: SPEC | I185: see line 129 -- spec and client error. doing at cost to get it completed | J185: San Jose | K185: GLOBALE - Global Industrial | L185: 1 | M185: 0 | N185: 99.95 | O185: Marlene Dyson | P185: =VLOOKUP(Table1[[#This Row],[Line Item Text Code]],$U$3:$V$7,2,FALSE) -> Specification Error | Q185: =Table1[[#This Row],[Ext. Cost]]-Table1[[#This Row],[Ext. Sell]] -> 99.95 | R185: =VLOOKUP(C185,Bookings!$A$1:$B$33,2,FALSE) -> 3879926.5 | S185: =IFERROR(VLOOKUP(D185,Bookings!E:F,2,FALSE),0) -> 23189.56 | T185: =IFERROR(VLOOKUP(Table1[[#This Row],[Order]],Bookings_with_AM_Report!A:L,12,FALSE),"N/A") -> Marena Brown
A186: 87326 | B186: 122 | C186: Olivia Gorfain | D186: Jones Lang Lasalle JLL | E186: Warehouse Storage | F186: December, 2024 (Billing Cycle: Nov 21 - Dec 20) | G186: STORE | H186: CUST | I186: customer | J186: San Francisco | K186: SERVICE - Service West- San Leandro | L186: 1 | M186: 0 | N186: 45.2 | O186: Nicole Lentini | P186: =VLOOKUP(Table1[[#This Row],[Line Item Text Code]],$U$3:$V$7,2,FALSE) -> Customer Accomodation | Q186: =Table1[[#This Row],[Ext. Cost]]-Table1[[#This Row],[Ext. Sell]] -> 45.2 | R186: =VLOOKUP(C186,Bookings!$A$1:$B$33,2,FALSE) -> 25594615 | S186: =IFERROR(VLOOKUP(D186,Bookings!E:F,2,FALSE),0) -> 0 | T186: =IFERROR(VLOOKUP(Table1[[#This Row],[Order]],Bookings_with_AM_Report!A:L,12,FALSE),"N/A") -> Anthony Pantaleoni,Josie Maitlen
A187: 87326 | B187: 124 | C187: Olivia Gorfain | D187: Jones Lang Lasalle JLL | E187: January, 2025 -STORAGE | F187: January, 2025 (Billing Cycle: Dec 21 - Jan 20) | G187: STORE | H187: CUST | I187: Storge for early arriving product | J187: San Francisco | K187: SERVICE - Service West- San Leandro | L187: 1 | M187: 0 | N187: 136.55 | O187: Nicole Lentini | P187: =VLOOKUP(Table1[[#This Row],[Line Item Text Code]],$U$3:$V$7,2,FALSE) -> Customer Accomodation | Q187: =Table1[[#This Row],[Ext. Cost]]-Table1[[#This Row],[Ext. Sell]] -> 136.55 | R187: =VLOOKUP(C187,Bookings!$A$1:$B$33,2,FALSE) -> 25594615 | S187: =IFERROR(VLOOKUP(D187,Bookings!E:F,2,FALSE),0) -> 0 | T187: =IFERROR(VLOOKUP(Table1[[#This Row],[Order]],Bookings_with_AM_Report!A:L,12,FALSE),"N/A") -> Anthony Pantaleoni,Josie Maitlen
A188: 87326 | B188: 125 | C188: Olivia Gorfain | D188: Jones Lang Lasalle JLL | E188: WAREHOUSE STORAGE | F188: September, 2024 (Billing Cycle: Aug 21 - Sep 20) 87326-85748 316444 06/27/2024 07/27/2024 30 $20 Min $0.63 10.0 $20.00 87326-85751 317066 07/16/2024 08/15/2024 30 $0.63 125.0 $78.75 87326-85755 317144 07/18/2024 08/17/2024 30 $0.63 60.0 $37.80 87326-85757 317720 08/06/2024 09/05/2024 15 $20 Min $0.63 50.0 $20.00 87326-85758 318049 08/14/2024 09/13/2024 7 $20 Min $0.63 110.0 $20.00 87326-85749 318120 08/15/2024 09/14/2024 6 $0.63 260.0 $32.76 | G188: FABR | H188: CUST | I188: Storage-early arriving product | J188: San Francisco | K188: SERVICE - Service West- San Leandro | L188: 1 | M188: 0 | N188: -209.31 | O188: Nicole Lentini | P188: =VLOOKUP(Table1[[#This Row],[Line Item Text Code]],$U$3:$V$7,2,FALSE) -> Customer Accomodation | Q188: =Table1[[#This Row],[Ext. Cost]]-Table1[[#This Row],[Ext. Sell]] -> -209.31 | R188: =VLOOKUP(C188,Bookings!$A$1:$B$33,2,FALSE) -> 25594615 | S188: =IFERROR(VLOOKUP(D188,Bookings!E:F,2,FALSE),0) -> 0 | T188: =IFERROR(VLOOKUP(Table1[[#This Row],[Order]],Bookings_with_AM_Report!A:L,12,FALSE),"N/A") -> Anthony Pantaleoni,Josie Maitlen
A189: 87326 | B189: 126 | C189: Olivia Gorfain | D189: Jones Lang Lasalle JLL | E189: Warehouse Storage | F189: September, 2024 (Billing Cycle: Aug 21 - Sep 20) 87326-85748 316444 06/27/2024 07/27/2024 30 $20 Min $0.63 10.0 $20.00 87326-85751 317066 07/16/2024 08/15/2024 30 $0.63 125.0 $78.75 87326-85755 317144 07/18/2024 08/17/2024 30 $0.63 60.0 $37.80 87326-85757 317720 08/06/2024 09/05/2024 15 $20 Min $0.63 50.0 $20.00 87326-85758 318049 08/14/2024 09/13/2024 7 $20 Min $0.63 110.0 $20.00 87326-85749 318120 08/15/2024 09/14/2024 6 $0.63 260.0 $32.76 | G189: STORE | H189: CUST | I189: Storage-early arriving product | J189: San Francisco | K189: SERVICE - Service West- San Leandro | L189: 1 | M189: 0 | N189: 209.31 | O189: Nicole Lentini | P189: =VLOOKUP(Table1[[#This Row],[Line Item Text Code]],$U$3:$V$7,2,FALSE) -> Customer Accomodation | Q189: =Table1[[#This Row],[Ext. Cost]]-Table1[[#This Row],[Ext. Sell]] -> 209.31 | R189: =VLOOKUP(C189,Bookings!$A$1:$B$33,2,FALSE) -> 25594615 | S189: =IFERROR(VLOOKUP(D189,Bookings!E:F,2,FALSE),0) -> 0 | T189: =IFERROR(VLOOKUP(Table1[[#This Row],[Order]],Bookings_with_AM_Report!A:L,12,FALSE),"N/A") -> Anthony Pantaleoni,Josie Maitlen
A190: 87326 | B190: 127 | C190: Olivia Gorfain | D190: Jones Lang Lasalle JLL | E190: Warehouse Storage | F190: February, 2025 (Billing Cycle: Jan 21 - Feb 20) | G190: STORE | H190: CUST | I190: STORAGE | J190: San Francisco | K190: SERVICE - Service West- San Leandro | L190: 1 | M190: 0 | N190: 100 | O190: Nicole Lentini | P190: =VLOOKUP(Table1[[#This Row],[Line Item Text Code]],$U$3:$V$7,2,FALSE) -> Customer Accomodation | Q190: =Table1[[#This Row],[Ext. Cost]]-Table1[[#This Row],[Ext. Sell]] -> 100 | R190: =VLOOKUP(C190,Bookings!$A$1:$B$33,2,FALSE) -> 25594615 | S190: =IFERROR(VLOOKUP(D190,Bookings!E:F,2,FALSE),0) -> 0 | T190: =IFERROR(VLOOKUP(Table1[[#This Row],[Order]],Bookings_with_AM_Report!A:L,12,FALSE),"N/A") -> Anthony Pantaleoni,Josie Maitlen
A191: 87326 | B191: 128 | C191: Olivia Gorfain | D191: Jones Lang Lasalle JLL | E191: Warehouse Storage | F191: February, 2025 (Billing Cycle: Jan 21 - Feb 20) | G191: STORE | H191: CUST | I191: STORAGE | J191: San Francisco | K191: SERVICE - Service West- San Leandro | L191: 1 | M191: 0 | N191: 67.25 | O191: Nicole Lentini | P191: =VLOOKUP(Table1[[#This Row],[Line Item Text Code]],$U$3:$V$7,2,FALSE) -> Customer Accomodation | Q191: =Table1[[#This Row],[Ext. Cost]]-Table1[[#This Row],[Ext. Sell]] -> 67.25 | R191: =VLOOKUP(C191,Bookings!$A$1:$B$33,2,FALSE) -> 25594615 | S191: =IFERROR(VLOOKUP(D191,Bookings!E:F,2,FALSE),0) -> 0 | T191: =IFERROR(VLOOKUP(Table1[[#This Row],[Order]],Bookings_with_AM_Report!A:L,12,FALSE),"N/A") -> Anthony Pantaleoni,Josie Maitlen
... A205: 87437 | B205: 13 | C205: Lela Huenergardt | D205: Jayson Architecture | E205: PM | F205: Project Management with true up and corrected the unit of measure to hours. | G205: PM-TAX | H205: MISC | I205: I missed that it wasn't hours so had to credit the line (original lie 4) and re-enter correctly for the cost. Sell is still on line 4. | J205: San Jose | K205: KBM-PM - KBM-Hogue Project Management | L205: 2.5 | M205: 0 | N205: 187.5 | O205: Marlene Dyson | P205: =VLOOKUP(Table1[[#This Row],[Line Item Text Code]],$U$3:$V$7,2,FALSE) -> Miscellaneous | Q205: =Table1[[#This Row],[Ext. Cost]]-Table1[[#This Row],[Ext. Sell]] -> 187.5 | R205: =VLOOKUP(C205,Bookings!$A$1:$B$33,2,FALSE) -> 3879926.5 | S205: =IFERROR(VLOOKUP(D205,Bookings!E:F,2,FALSE),0) -> 492.3 | T205: =IFERROR(VLOOKUP(Table1[[#This Row],[Order]],Bookings_with_AM_Report!A:L,12,FALSE),"N/A") -> N/A
A206: 87536 | B206: 483 | C206: Olivia Gorfain | D206: Davis Polk & Wardwell LLP | E206: MILEAGE AND PARKING | G206: TRV | H206: MISC | I206: Travel | J206: San Francisco | K206: WENDYST - Wendy Stark | L206: 1 | M206: 0 | N206: 45.31 | O206: Nicole Lentini | P206: =VLOOKUP(Table1[[#This Row],[Line Item Text Code]],$U$3:$V$7,2,FALSE) -> Miscellaneous | Q206: =Table1[[#This Row],[Ext. Cost]]-Table1[[#This Row],[Ext. Sell]] -> 45.31 | R206: =VLOOKUP(C206,Bookings!$A$1:$B$33,2,FALSE) -> 25594615 | S206: =IFERROR(VLOOKUP(D206,Bookings!E:F,2,FALSE),0) -> 670595.27 | T206: =IFERROR(VLOOKUP(Table1[[#This Row],[Order]],Bookings_with_AM_Report!A:L,12,FALSE),"N/A") -> Torrey Crell
A207: 87536 | B207: 485 | C207: Olivia Gorfain | D207: Davis Polk & Wardwell LLP | E207: SHIPPING AND HANDLING | F207: REF 1599040267 PC00799995 (RETURNING) | G207: SHIP | H207: SPEC | I207: Cost to return incorrect product | J207: San Francisco | K207: FEDEXFR - Fedex Freight | L207: 1 | M207: 0 | N207: 2176.51 | O207: Nicole Lentini | P207: =VLOOKUP(Table1[[#This Row],[Line Item Text Code]],$U$3:$V$7,2,FALSE) -> Specification Error | Q207: =Table1[[#This Row],[Ext. Cost]]-Table1[[#This Row],[Ext. Sell]] -> 2176.51 | R207: =VLOOKUP(C207,Bookings!$A$1:$B$33,2,FALSE) -> 25594615 | S207: =IFERROR(VLOOKUP(D207,Bookings!E:F,2,FALSE),0) -> 670595.27 | T207: =IFERROR(VLOOKUP(Table1[[#This Row],[Order]],Bookings_with_AM_Report!A:L,12,FALSE),"N/A") -> Torrey Crell
A208: 87536 | B208: 486 | C208: Olivia Gorfain | D208: Davis Polk & Wardwell LLP | E208: SHIPPING AND HANDLING-8928138516 | F208: REF 1599040267 BOL 8928138516 PC00799995 (RETURNING) | G208: SHIP | H208: SPEC | I208: Cost to return incorrect product | J208: San Francisco | K208: FEDEXFR - Fedex Freight | L208: 1 | M208: 0 | N208: 823.45 | O208: Nicole Lentini | P208: =VLOOKUP(Table1[[#This Row],[Line Item Text Code]],$U$3:$V$7,2,FALSE) -> Specification Error | Q208: =Table1[[#This Row],[Ext. Cost]]-Table1[[#This Row],[Ext. Sell]] -> 823.45 | R208: =VLOOKUP(C208,Bookings!$A$1:$B$33,2,FALSE) -> 25594615 | S208: =IFERROR(VLOOKUP(D208,Bookings!E:F,2,FALSE),0) -> 670595.27 | T208: =IFERROR(VLOOKUP(Table1[[#This Row],[Order]],Bookings_with_AM_Report!A:L,12,FALSE),"N/A") -> Torrey Crell
A209: 87536 | B209: 490 | C209: Olivia Gorfain | D209: Davis Polk & Wardwell LLP | E209: 1579 | F209: Seating Parts 1579 complete seat and back | G209: PRO | H209: CUST | I209: This is punch/client accommodation for stool seat replacements. The originals went missing on site while we were waiting for the base replacements. | J209: San Francisco | K209: BERNHAR - Bernhardt | L209: 4 | M209: 0 | N209: 502.2 | O209: Nicole Lentini | P209: =VLOOKUP(Table1[[#This Row],[Line Item Text Code]],$U$3:$V$7,2,FALSE) -> Customer Accomodation | Q209: =Table1[[#This Row],[Ext. Cost]]-Table1[[#This Row],[Ext. Sell]] -> 502.2 | R209: =VLOOKUP(C209,Bookings!$A$1:$B$33,2,FALSE) -> 25594615 | S209: =IFERROR(VLOOKUP(D209,Bookings!E:F,2,FALSE),0) -> 670595.27 | T209: =IFERROR(VLOOKUP(Table1[[#This Row],[Order]],Bookings_with_AM_Report!A:L,12,FALSE),"N/A") -> Torrey Crell
A210: 87536 | B210: 491 | C210: Olivia Gorfain | D210: Davis Polk & Wardwell LLP | E210: 3111-225 | F210: Elan-Saddle | G210: PRO | H210: CUST | I210: This is punch/client accommodation for stool seat replacements. The originals went missing on site while we were waiting for the base replacements. | J210: San Francisco | K210: BERNHAR - Bernhardt | L210: 116 | M210: 0 | N210: 1624 | O210: Nicole Lentini | P210: =VLOOKUP(Table1[[#This Row],[Line Item Text Code]],$U$3:$V$7,2,FALSE) -> Customer Accomodation | Q210: =Table1[[#This Row],[Ext. Cost]]-Table1[[#This Row],[Ext. Sell]] -> 1624 | R210: =VLOOKUP(C210,Bookings!$A$1:$B$33,2,FALSE) -> 25594615 | S210: =IFERROR(VLOOKUP(D210,Bookings!E:F,2,FALSE),0) -> 670595.27 | T210: =IFERROR(VLOOKUP(Table1[[#This Row],[Order]],Bookings_with_AM_Report!A:L,12,FALSE),"N/A") -> Torrey Crell
A211: 87536 | B211: 492 | C211: Olivia Gorfain | D211: Davis Polk & Wardwell LLP | E211: FREIGHT | F211: Freight | G211: SHIP | H211: CUST | I211: This is punch/client accommodation for stool seat replacements. The originals went missing on site while we were waiting for the base replacements. | J211: San Francisco | K211: BERNHAR - Bernhardt | L211: 1 | M211: 0 | N211: 150 | O211: Nicole Lentini | P211: =VLOOKUP(Table1[[#This Row],[Line Item Text Code]],$U$3:$V$7,2,FALSE) -> Customer Accomodation | Q211: =Table1[[#This Row],[Ext. Cost]]-Table1[[#This Row],[Ext. Sell]] -> 150 | R211: =VLOOKUP(C211,Bookings!$A$1:$B$33,2,FALSE) -> 25594615 | S211: =IFERROR(VLOOKUP(D211,Bookings!E:F,2,FALSE),0) -> 670595.27 | T211: =IFERROR(VLOOKUP(Table1[[#This Row],[Order]],Bookings_with_AM_Report!A:L,12,FALSE),"N/A") -> Torrey Crell
A212: 87536 | B212: 496 | C212: Olivia Gorfain | D212: Davis Polk & Wardwell LLP | E212: SHIPPING AND HANDLING | F212: Shipping and handling /PJT GUARANTEED FRT 6% 150.00 REQUESTED DEL ASAP OM1 SHIP | G212: SHIP | H212: CUST | I212: customer | J212: San Francisco | K212: BERNHAR - Bernhardt | L212: 1 | M212: 0 | N212: 150 | O212: Nicole Lentini | P212: =VLOOKUP(Table1[[#This Row],[Line Item Text Code]],$U$3:$V$7,2,FALSE) -> Customer Accomodation | Q212: =Table1[[#This Row],[Ext. Cost]]-Table1[[#This Row],[Ext. Sell]] -> 150 | R212: =VLOOKUP(C212,Bookings!$A$1:$B$33,2,FALSE) -> 25594615 | S212: =IFERROR(VLOOKUP(D212,Bookings!E:F,2,FALSE),0) -> 670595.27 | T212: =IFERROR(VLOOKUP(Table1[[#This Row],[Order]],Bookings_with_AM_Report!A:L,12,FALSE),"N/A") -> Torrey Crell
A213: 87536 | B213: 497 | C213: Olivia Gorfain | D213: Davis Polk & Wardwell LLP | E213: MILEAGE AND PARKING | G213: TRV | H213: MISC | I213: Travel | J213: San Francisco | K213: WENDYST - Wendy Stark | L213: 1 | M213: 0 | N213: 32.97 | O213: Nicole Lentini | P213: =VLOOKUP(Table1[[#This Row],[Line Item Text Code]],$U$3:$V$7,2,FALSE) -> Miscellaneous | Q213: =Table1[[#This Row],[Ext. Cost]]-Table1[[#This Row],[Ext. Sell]] -> 32.97 | R213: =VLOOKUP(C213,Bookings!$A$1:$B$33,2,FALSE) -> 25594615 | S213: =IFERROR(VLOOKUP(D213,Bookings!E:F,2,FALSE),0) -> 670595.27 | T213: =IFERROR(VLOOKUP(Table1[[#This Row],[Order]],Bookings_with_AM_Report!A:L,12,FALSE),"N/A") -> Torrey Crell
...

Sheet Bookings
A1: Salesperson | B1: Sum of Total Sell | E1: Client | F1: Sum of Total Sell | I1: AM | J1: Sum of Total Sell
A2: Alex Blangeres | B2: 3992449.5 | E2: 201 Spear Property, LLC | F2: 291498.43 | J2: 151844.66
A3: Anthony Pantaleoni | B3: 325857.38 | E3: 345 California L.P. | F3: 6786 | I3: Alex Blangeres | J3: 0
A4: Chris Cicisly | B4: 6995960.2 | E4: 6Sense | F4: 77925 | I4: Andrea Greever | J4: 501309.46
A5: Erika Duarte | B5: 3309.31 | E5: 84 West LLC | F5: 79008.91 | I5: Anthony Pantaleoni | J5: 11090765
A6: Farrah Race | B6: 17764.57 | E6: AAA Northern California, Utah & Nevada | F6: 1690928.3 | I6: Anthony Pantaleoni,Hana Estrada | J6: 189553.69
A7: Genesis Rita | B7: 1079.55 | E7: ABC10 | F7: 424.02 | I7: Anthony Pantaleoni,Josie Maitlen | J7: 0
A8: Jenni Lombardi | B8: 3917134.9 | E8: Accel Management Co | F8: 106367 | I8: Anthony Pantaleoni,Melissa Rokes | J8: 846951.72
A9: Jill Marsh | B9: 6210075.2 | E9: Acosta & Sons Inc | F9: 923.07 | I9: Anthony Pantaleoni,Torrey Crell | J9: 1325
A10: Kate Ingelstrom | B10: 2600398.1 | E10: Adrian Wall | F10: 799.5 | I10: Carina Collison | J10: 2139565
A11: Kimi Katsuyoshi | B11: 17992.6 | E11: AdVal Properties | F11: 11392.64 | I11: Casey Fleming | J11: 501061.62
A12: Lela Huenergardt | B12: 3879926.5 | E12: Adventist | F12: 0 | I12: Casey Fleming,Norma Lopez | J12: 66593.24
A13: Lindsay Hanief | B13: 11238.25 | E13: Aedis Architecture | F13: 0 | I13: Casey Fleming,Troy Ocariza | J13: 0
A14: Mark Dailey | B14: 1917863.2 | E14: Affordable Interior Systems | F14: 450 | I14: Chris Cicisly | J14: 4973.24
... A37: Grand Total | B37: 84735438 | E37: Bay Area Headquarters Authority | F37: 339398.68 | I37: Hana Estrada,Melissa Rokes,Torrey Crell | J37: 0
E38: Be Workplace Design | F38: 22827.78 | I38: Hana Estrada,Paul Razo | J38: 183647.18
E39: Berkeley Endowment Management Company | F39: 10780 | I39: Hana Estrada,Torrey Crell | J39: 5939.76
E40: Berkeley Research Group, LLC | F40: 9499.6 | I40: Jenni Lombardi | J40: 6601711.8
E41: Best, Best & Krieger LLP | F41: 6246.15 | I41: Jessica Ramirez | J41: 1853042.4
E42: BioMed Realty | F42: 0 | I42: Jillian Galla | J42: 206957.95
E43: bioMerieux | F43: 0 | I43: Josie Maitlen | J43: 1141056.4
E44: Blue Bottle Coffee | F44: 38549.33 | I44: Josie Maitlen,Melissa Rokes | J44: 25249.83
E45: Boston Properties | F45: 0 | I45: Josie Maitlen,Torrey Crell | J45: 5075193.4
E46: Boston Properties Limited Partnership | F46: 591585.21 | I46: Kate Ingelstrom | J46: 817.81
E47: Boutin Jones, Inc. | F47: 11026.59 | I47: Kimi Katsuyoshi | J47: 1135782.4
E48: Brandy Dunkel | F48: 338.16 | I48: Kimi Katsuyoshi,Melissa Avalos | J48: 1047400.2
E49: BridgeBio Pharma, Inc | F49: 660 | I49: Kimi Katsuyoshi,Saoirse O'Connor | J49: 658
... E105: Crowdstrike | F105: 22810.07 | I105: Grand Total | J105: 84735438
E106: Crunchyroll LLC | F106: 91858
E107: Cushman & Wakefield | F107: 40007
E108: CVC Advisors (U.S.), Inc | F108: 1050
E109: Cytokinetics | F109: 2174302
E110: DataRobot | F110: 0
E111: DataSpan Holdings, Inc | F111: 0
E112: Dauphin | F112: 190
E113: David Gensler | F113: 1167.75
E114: Davis Polk & Wardwell LLP | F114: 670595.27
E115: Debner, Inc | F115: 725
E116: Deep Origin | F116: 44523.75
E117: Defense Contract Management Agency | F117: 3309.31
... E442: Grand Total | F442: 84735438

Sheet Bookings_with_AM_Report
A1: Order # | B1: Activity Date | C1: Customer | D1: Salesperson | E1: Company | F1: New Sell | G1: Adj Sell | H1: Total Sell | I1: Total Cost | J1: GP | K1: GP % | L1: Account Manager
A2: 88802 | B2: 45659 | C2: Hines West LLC | D2: Anthony Pantaleoni | E2: San Francisco | F2: 0 | G2: 0 | H2: 0 | I2: -102 | J2: 102 | K2: 0 | L2: Anthony Pantaleoni,Hana Estrada
A3: 82661 | B3: 45659 | C3: WelbeHealth, LLC | D3: Alex Blangeres | E3: Sacramento | F3: 0 | G3: 0 | H3: 0 | I3: 523.45 | J3: -523.45 | K3: 0 | L3: Farrah Race
A4: 85709 | B4: 45659 | C4: WelbeHealth, LLC | D4: Alex Blangeres | E4: Sacramento | F4: 0 | G4: 0 | H4: 0 | I4: 66.99 | J4: -66.99 | K4: 0 | L4: Farrah Race
A5: 85928 | B5: 45659 | C5: E-Commerce Orders | D5: Norma Lopez | E5: San Jose | F5: 0 | G5: 0 | H5: 0 | I5: 18.77 | J5: -18.77 | K5: 0 | L5: Norma Lopez
A6: 86929 | B6: 45659 | C6: Littler Mendelson, P.C. | D6: Kate Ingelstrom | E6: San Jose | F6: 0 | G6: 378.38 | H6: 378.38 | I6: 280 | J6: 98.38 | K6: 0.26000317 | L6: Genesis Rita
A7: 87688 | B7: 45659 | C7: AAA Northern California, Utah & Nevada | D7: Mark Dailey | E7: Sacramento | F7: 0 | G7: 0 | H7: 0 | I7: 483.43 | J7: -483.43 | K7: 0 | L7: Rayna Mitchell
A8: 87690 | B8: 45659 | C8: AAA Northern California, Utah & Nevada | D8: Mark Dailey | E8: Sacramento | F8: 0 | G8: 0 | H8: 0 | I8: 42.01 | J8: -42.01 | K8: 0 | L8: Rayna Mitchell
A9: 87808 | B9: 45659 | C9: Intuit-OR 205 | D9: Norma Lopez | E9: San Jose | F9: 0 | G9: 0 | H9: 0 | I9: 526.2 | J9: -526.2 | K9: 0 | L9: Jessica Ramirez
A10: 88845 | B10: 45659 | C10: Stanford University | D10: Jill Marsh | E10: San Francisco | F10: 0 | G10: 0 | H10: 0 | I10: 25.7 | J10: -25.7 | K10: 0 | L10: Lindsay Hanief
A11: 88871 | B11: 45659 | C11: Intuit-OR 205 | D11: Norma Lopez | E11: San Jose | F11: 0 | G11: 0 | H11: 0 | I11: 674.7 | J11: -674.7 | K11: 0 | L11: Jessica Ramirez
A12: 89045 | B12: 45659 | C12: Qatalyst Partners LP | D12: Chris Cicisly | E12: San Jose | F12: 0 | G12: 0 | H12: 0 | I12: 0 | J12: 0 | K12: 0 | L12: Mary Sparacino
A13: 89416 | B13: 45659 | C13: Best, Best & Krieger LLP | D13: Troy Ocariza | E13: San Jose | F13: 0 | G13: 0 | H13: 0 | I13: -131.77 | J13: 131.77 | K13: 0 | L13: Troy Ocariza
... A6633: 93476 | B6633: 45863 | C6633: Littler Mendelson, P.C. | D6633: Kate Ingelstrom | E6633: San Jose | F6633: 0 | G6633: 48.5 | H6633: 48.5 | I6633: 36.86 | J6633: 11.64 | K6633: 0.24 | L6633: Genesis Rita
A6634: 93572 | B6634: 45863 | C6634: Owen Cunningham | D6634: Matt Denning | E6634: San Francisco | F6634: 950 | G6634: 0 | H6634: 950 | I6634: 950 | J6634: 0 | K6634: 0
A6635: 93654 | B6635: 45863 | C6635: Wilson Sonsini Goodrich & Rosati | D6635: Jenni Lombardi | E6635: San Jose | F6635: 3750 | G6635: 0 | H6635: 3750 | I6635: 0 | J6635: 3750 | K6635: 1 | L6635: Jenni Lombardi
A6636: 93656 | B6636: 45863 | C6636: Wilson Sonsini Goodrich & Rosati | D6636: Jenni Lombardi | E6636: San Jose | F6636: 200 | G6636: 0 | H6636: 200 | I6636: 0 | J6636: 200 | K6636: 1 | L6636: Jenni Lombardi
A6637: 93657 | B6637: 45863 | C6637: Wilson Sonsini Goodrich & Rosati | D6637: Jenni Lombardi | E6637: San Jose | F6637: 3025 | G6637: 0 | H6637: 3025 | I6637: 0 | J6637: 3025 | K6637: 1 | L6637: Jenni Lombardi
A6638: 93658 | B6638: 45863 | C6638: Wilson Sonsini Goodrich & Rosati | D6638: Jenni Lombardi | E6638: San Jose | F6638: 900 | G6638: 0 | H6638: 900 | I6638: 0 | J6638: 900 | K6638: 1 | L6638: Jenni Lombardi
A6639: 93659 | B6639: 45863 | C6639: Wilson Sonsini Goodrich & Rosati | D6639: Jenni Lombardi | E6639: San Jose | F6639: 200 | G6639: 0 | H6639: 200 | I6639: 0 | J6639: 200 | K6639: 1 | L6639: Jenni Lombardi
A6640: 93660 | B6640: 45863 | C6640: Wilson Sonsini Goodrich & Rosati | D6640: Jenni Lombardi | E6640: San Jose | F6640: 25 | G6640: 0 | H6640: 25 | I6640: 0 | J6640: 25 | K6640: 1 | L6640: Jenni Lombardi
A6641: 93673 | B6641: 45863 | C6641: Levi Strauss & Co | D6641: Owen Cunningham | E6641: San Francisco | F6641: 751 | G6641: 0 | H6641: 751 | I6641: 751 | J6641: 0 | K6641: 0 | L6641: Josie Maitlen,Torrey Carroll
A6642: 93676 | B6642: 45863 | C6642: Wilson Sonsini Goodrich & Rosati | D6642: Jenni Lombardi | E6642: San Jose | F6642: 1370.62 | G6642: 0 | H6642: 1370.62 | I6642: 1165 | J6642: 205.62 | K6642: 0.1500197 | L6642: Jenni Lombardi
A6643: 93688 | B6643: 45863 | C6643: Intuit-OR 205 | D6643: Norma Lopez | E6643: San Jose | F6643: 3854.46 | G6643: 0 | H6643: 3854.46 | I6643: 2939.03 | J6643: 915.43 | K6643: 0.2374989 | L6643: Norma Lopez
A6644: 93713 | B6644: 45863 | C6644: Intuit-OR 205 | D6644: Norma Lopez | E6644: San Jose | F6644: 31595.83 | G6644: 0 | H6644: 31595.83 | I6644: 21607.5 | J6644: 9988.33 | K6644: 0.31612811 | L6644: Jessica Ramirez
A6645: 93740 | B6645: 45863 | C6645: Wilson Sonsini Goodrich & Rosati | D6645: Jenni Lombardi | E6645: San Jose | F6645: 5004.96 | G6645: 0 | H6645: 5004.96 | I6645: 4254.22 | J6645: 750.74 | K6645: 0.1499992 | L6645: Jenni Lombardi
A6646: 93742 | B6646: 45863 | C6646: Wilson Sonsini Goodrich & Rosati | D6646: Jenni Lombardi | E6646: San Jose | F6646: 6120.08 | G6646: 0 | H6646: 6120.08 | I6646: 5202.07 | J6646: 918.01 | K6646: 0.14999967 | L6646: Jenni Lombardi
... A6652: 93537 | B6652: 45866 | C6652: Chan Zuckerberg Initiative | D6652: Owen Cunningham | E6652: San Francisco | F6652: 0 | G6652: 0 | H6652: 0 | I6652: 841.53 | J6652: -841.53 | K6652: 0 | L6652: Frances Kim,Kimi Katsuyoshi
A6653: 93572 | B6653: 45866 | C6653: Owen Cunningham | D6653: Matt Denning | E6653: San Francisco | F6653: 1900 | G6653: 0 | H6653: 1900 | I6653: 1900 | J6653: 0 | K6653: 0
A6654: 86211 | B6654: 45866 | C6654: Shorenstein | D6654: Jill Marsh | E6654: San Francisco | F6654: 0 | G6654: 3584.03 | H6654: 3584.03 | I6654: 3069.36 | J6654: 514.67 | K6654: 0.14360092 | L6654: Paul Razo
A6655: 86702 | B6655: 45866 | C6655: Charles Schwab | D6655: Jill Marsh | E6655: San Francisco | F6655: 0 | G6655: -2306.58 | H6655: -2306.58 | I6655: 0 | J6655: -2306.58 | K6655: 1 | L6655: Paul Razo
A6656: 87104 | B6656: 45866 | C6656: Third District Court of Appeal | D6656: Alex Blangeres | E6656: Sacramento | F6656: 0 | G6656: 0 | H6656: 0 | I6656: -150 | J6656: 150 | K6656: 0 | L6656: Farrah Race
A6657: 88772 | B6657: 45866 | C6657: Patient Square Capital | D6657: Owen Cunningham | E6657: San Francisco | F6657: 0 | G6657: 2100 | H6657: 2100 | I6657: 1503.81 | J6657: 596.19 | K6657: 0.2839 | L6657: Kimi Katsuyoshi
A6658: 89645 | B6658: 45866 | C6658: Boston Properties Limited Partnership | D6658: Olivia Gorfain | E6658: San Francisco | F6658: 5472.12 | G6658: 0 | H6658: 5472.12 | I6658: 4651.3 | J6658: 820.82 | K6658: 0.15000037 | L6658: Josie Maitlen
A6659: 90206 | B6659: 45866 | C6659: AAA Northern California, Utah & Nevada | D6659: Mark Dailey | E6659: Sacramento | F6659: 0 | G6659: 0 | H6659: 0 | I6659: -1768.75 | J6659: 1768.75 | K6659: 0 | L6659: Rayna Mitchell
A6660: 90212 | B6660: 45866 | C6660: Longfellow Real Estate Partners LLC | D6660: Anthony Pantaleoni | E6660: San Francisco | F6660: 5056.09 | G6660: 0 | H6660: 5056.09 | I6660: 5196.25 | J6660: -140.16 | K6660: -0.02772103 | L6660: Anthony Pantaleoni,Melissa Rokes
A6661: 90472 | B6661: 45866 | C6661: County of Santa Clara | D6661: Lela Huenergardt | E6661: San Jose | F6661: 0 | G6661: 0 | H6661: 0 | I6661: 223.42 | J6661: -223.42 | K6661: 0 | L6661: Megan Ewers
A6662: 90822 | B6662: 45866 | C6662: Dodge and Cox | D6662: Jill Marsh | E6662: San Francisco | F6662: 0 | G6662: 1315 | H6662: 1315 | I6662: 917.28 | J6662: 397.72 | K6662: 0.30244867 | L6662: Frances Kim
A6663: 90891 | B6663: 45866 | C6663: Judicial Council of California | D6663: Alex Blangeres | E6663: Sacramento | F6663: 0 | G6663: 0 | H6663: 0 | I6663: -76.55 | J6663: 76.55 | K6663: 0 | L6663: Rayna Mitchell
A6664: 91126 | B6664: 45866 | C6664: Simpson Thacher & Bartlett LLP | D6664: Olivia Gorfain | E6664: San Francisco | F6664: 0 | G6664: -1802423.3 | H6664: -1802423.3 | I6664: 0 | J6664: -1802423.3 | K6664: 1 | L6664: Anthony Pantaleoni
A6665: 91459 | B6665: 45866 | C6665: Littler Mendelson, P.C. | D6665: Kate Ingelstrom | E6665: San Jose | F6665: 0 | G6665: 378.38 | H6665: 378.38 | I6665: 280 | J6665: 98.38 | K6665: 0.26000317 | L6665: Genesis Rita
... A6708: 93173 | B6708: 45867 | C6708: Littler Mendelson, P.C. | D6708: Kate Ingelstrom | E6708: San Jose | F6708: 0 | G6708: 0 | H6708: 0 | I6708: 677.66 | J6708: -677.66 | K6708: 0 | L6708: Genesis Rita
A6709: 93472 | B6709: 45867 | C6709: Intuit-OR 205 | D6709: Norma Lopez | E6709: San Jose | F6709: 116367.28 | G6709: 0 | H6709: 116367.28 | I6709: 95277.65 | J6709: 21089.63 | K6709: 0.18123333
A6710: 93537 | B6710: 45867 | C6710: Chan Zuckerberg Initiative | D6710: Owen Cunningham | E6710: San Francisco | F6710: 0 | G6710: 0 | H6710: 0 | I6710: -5.25 | J6710: 5.25 | K6710: 0 | L6710: Frances Kim,Kimi Katsuyoshi
A6711: 93589 | B6711: 45867 | C6711: Sequoia Capital Operations, LLC | D6711: Owen Cunningham | E6711: San Francisco | F6711: 20703.8 | G6711: 0 | H6711: 20703.8 | I6711: 15498.13 | J6711: 5205.67 | K6711: 0.25143549
A6712: 93607 | B6712: 45867 | C6712: Intuit-OR 205 | D6712: Norma Lopez | E6712: San Jose | F6712: 112188.51 | G6712: 0 | H6712: 112188.51 | I6712: 91015.85 | J6712: 21172.66 | K6712: 0.18872396 | L6712: Norma Lopez
A6713: 93630 | B6713: 45867 | C6713: San Jose State University | D6713: Matt Fleming | E6713: San Jose | F6713: 0 | G6713: 3600 | H6713: 3600 | I6713: 2673.01 | J6713: 926.99 | K6713: 0.25749722 | L6713: Casey Fleming,Matt Fleming
A6714: 93671 | B6714: 45867 | C6714: Grammarly | D6714: Owen Cunningham | E6714: San Francisco | F6714: 0 | G6714: -18244 | H6714: -18244 | I6714: -13273.49 | J6714: -4970.51 | K6714: 0.27244628 | L6714: Frances Kim
A6715: 93675 | B6715: 45867 | C6715: Google, LLC | D6715: Olivia Gorfain | E6715: San Jose | F6715: 0 | G6715: -14261 | H6715: -14261 | I6715: 5619.47 | J6715: -19880.47 | K6715: 1.3940446 | L6715: Genesis Rita
A6716: 93722 | B6716: 45867 | C6716: Simpson Thacher & Bartlett LLP | D6716: Olivia Gorfain | E6716: San Francisco | F6716: 0 | G6716: -1298743 | H6716: -1298743 | I6716: -857170.38 | J6716: -441572.62 | K6716: 0.34 | L6716: Anthony Pantaleoni
A6717: 93723 | B6717: 45867 | C6717: Simpson Thacher & Bartlett LLP | D6717: Olivia Gorfain | E6717: San Francisco | F6717: 0 | G6717: -2598281 | H6717: -2598281 | I6717: -1714865.5 | J6717: -883415.54 | K6717: 0.34 | L6717: Anthony Pantaleoni
A6718: 93724 | B6718: 45867 | C6718: Simpson Thacher & Bartlett LLP | D6718: Olivia Gorfain | E6718: San Francisco | F6718: 0 | G6718: -176373.6 | H6718: -176373.6 | I6718: 0 | J6718: -176373.6 | K6718: 1 | L6718: Anthony Pantaleoni
A6719: 93756 | B6719: 45867 | C6719: Silicon Valley Mechanical, Inc | D6719: Kate Ingelstrom | E6719: San Jose | F6719: 13780.18 | G6719: 0 | H6719: 13780.18 | I6719: 10250.63 | J6719: 3529.55 | K6719: 0.25613236 | L6719: Genesis Rita
A6720: 93766 | B6720: 45867 | C6720: Hitachi Energy | D6720: Chris Cicisly | E6720: San Jose | F6720: 225 | G6720: 0 | H6720: 225 | I6720: 0 | J6720: 225 | K6720: 1 | L6720: Mary Sparacino
A6721: 93769 | B6721: 45867 | C6721: Judicial Council of California | D6721: Alex Blangeres | E6721: Sacramento | F6721: 177 | G6721: 0 | H6721: 177 | I6721: 125 | J6721: 52 | K6721: 0.29378531 | L6721: Rayna Mitchell
A6722: 90506 | B6722: 45868 | C6722: Grammarly | D6722: Owen Cunningham | E6722: San Francisco | F6722: 0 | G6722: 0 | H6722: 0 | I6722: 0.6 | J6722: -0.6 | K6722: 0 | L6722: Frances Kim
A6723: 90995 | B6723: 45868 | C6723: Cytokinetics | D6723: Chris Cicisly | E6723: San Jose | F6723: 0 | G6723: 9915 | H6723: 9915 | I6723: 7614.26 | J6723: 2300.74 | K6723: 0.23204639 | L6723: Mary Sparacino
... A6765: 93234 | B6765: 45868 | C6765: California State University, Sacramento | D6765: Simon Sheppard | E6765: Sacramento | F6765: 53695.54 | G6765: 0 | H6765: 53695.54 | I6765: 44000.67 | J6765: 9694.87 | K6765: 0.18055261 | L6765: Andrea Greever
A6766: 93472 | B6766: 45868 | C6766: Intuit-OR 205 | D6766: Norma Lopez | E6766: San Jose | F6766: 0 | G6766: 675.68 | H6766: 675.68 | I6766: 540.54 | J6766: 135.14 | K6766: 0.20000592
A6767: 93537 | B6767: 45868 | C6767: Chan Zuckerberg Initiative | D6767: Owen Cunningham | E6767: San Francisco | F6767: 0 | G6767: 1.47 | H6767: 1.47 | I6767: -0.37 | J6767: 1.84 | K6767: 1.2517007 | L6767: Frances Kim,Kimi Katsuyoshi
A6768: 93671 | B6768: 45868 | C6768: Grammarly | D6768: Owen Cunningham | E6768: San Francisco | F6768: 0 | G6768: 13.13 | H6768: 13.13 | I6768: 9.78 | J6768: 3.35 | K6768: 0.2551409 | L6768: Frances Kim
A6769: 93688 | B6769: 45868 | C6769: Intuit-OR 205 | D6769: Norma Lopez | E6769: San Jose | F6769: 0 | G6769: 0 | H6769: 0 | I6769: 85.68 | J6769: -85.68 | K6769: 0 | L6769: Norma Lopez
A6770: 93708 | B6770: 45868 | C6770: E&J Gallo Winery | D6770: Rayna Mitchell | E6770: Sacramento | F6770: 2811 | G6770: 0 | H6770: 2811 | I6770: 2314.75 | J6770: 496.25 | K6770: 0.1765386 | L6770: Rayna Mitchell
A6771: 93761 | B6771: 45868 | C6771: PFM Health Sciences | D6771: Nick Christianson | E6771: San Jose | F6771: 12673.75 | G6771: 0 | H6771: 12673.75 | I6771: 8877.68 | J6771: 3796.07 | K6771: 0.29952224 | L6771: Carina Collison
A6772: 93765 | B6772: 45868 | C6772: Marin County Free Library | D6772: Lela Huenergardt | E6772: San Jose | F6772: 340.13 | G6772: 0 | H6772: 340.13 | I6772: 0 | J6772: 340.13 | K6772: 1 | L6772: Lela Huenergardt,Marena Brown
A6773: 93767 | B6773: 45868 | C6773: County of Santa Clara | D6773: Lela Huenergardt | E6773: San Jose | F6773: 3009.05 | G6773: 0 | H6773: 3009.05 | I6773: 2347.12 | J6773: 661.93 | K6773: 0.21997973 | L6773: Gina Ortis,Megan Ewers
A6774: 93779 | B6774: 45868 | C6774: San Jose State University | D6774: Matt Fleming | E6774: San Jose | F6774: 2160 | G6774: 0 | H6774: 2160 | I6774: 1618.86 | J6774: 541.14 | K6774: 0.25052778 | L6774: Casey Fleming,Matt Fleming
A6775: 93787 | B6775: 45868 | C6775: Intuit E-Commerce Orders | D6775: Norma Lopez | E6775: San Jose | F6775: 1651 | G6775: 0 | H6775: 1651 | I6775: 1276.4 | J6775: 374.6 | K6775: 0.22689279 | L6775: Norma Lopez
A6776: 93790 | B6776: 45868 | C6776: Intuit E-Commerce Orders | D6776: Norma Lopez | E6776: San Jose | F6776: 1651 | G6776: 0 | H6776: 1651 | I6776: 1203.9 | J6776: 447.1 | K6776: 0.27080557 | L6776: Norma Lopez
A6777: 93793 | B6777: 45868 | C6777: Intuit E-Commerce Orders | D6777: Norma Lopez | E6777: San Jose | F6777: 1651 | G6777: 0 | H6777: 1651 | I6777: 1183.4 | J6777: 467.6 | K6777: 0.28322229 | L6777: Norma Lopez
A6778: 93794 | B6778: 45868 | C6778: Intuit E-Commerce Orders | D6778: Norma Lopez | E6778: San Jose | F6778: 1514.18 | G6778: 0 | H6778: 1514.18 | I6778: 1044 | J6778: 470.18 | K6778: 0.3105179 | L6778: Norma Lopez
... A6781: 93210 | B6781: 45869 | C6781: Medley Partners Management LLC | D6781: Jill Marsh | E6781: San Francisco | F6781: 0 | G6781: 0 | H6781: 0 | I6781: 5.19 | J6781: -5.19 | K6781: 0 | L6781: Chryslyn Perkins
A6782: 93472 | B6782: 45869 | C6782: Intuit-OR 205 | D6782: Norma Lopez | E6782: San Jose | F6782: 0 | G6782: 0 | H6782: 0 | I6782: -0.13 | J6782: 0.13 | K6782: 0
A6783: 93571 | B6783: 45869 | C6783: Eastdil Secured | D6783: Olivia Gorfain | E6783: San Francisco | F6783: 0 | G6783: 0 | H6783: 0 | I6783: -60.32 | J6783: 60.32 | K6783: 0 | L6783: Paul Razo
A6784: 93706 | B6784: 45869 | C6784: First Northern Bank | D6784: Rayna Mitchell | E6784: Sacramento | F6784: 3077.45 | G6784: 0 | H6784: 3077.45 | I6784: 2465.38 | J6784: 612.07 | K6784: 0.19888869 | L6784: Rayna Mitchell
A6785: 93718 | B6785: 45869 | C6785: Intuit E-Commerce Orders | D6785: Norma Lopez | E6785: San Jose | F6785: 1651 | G6785: 0 | H6785: 1651 | I6785: 1183.4 | J6785: 467.6 | K6785: 0.28322229 | L6785: Norma Lopez
A6786: 89795 | B6786: 45869 | C6786: Paramount Group | D6786: Olivia Gorfain | E6786: San Francisco | F6786: 0 | G6786: 0 | H6786: 0 | I6786: -1162.5 | J6786: 1162.5 | K6786: 0 | L6786: Melissa Rokes
A6787: 90207 | B6787: 45869 | C6787: AAA Northern California, Utah & Nevada | D6787: Mark Dailey | E6787: Sacramento | F6787: 0 | G6787: 0 | H6787: 0 | I6787: 13.75 | J6787: -13.75 | K6787: 0 | L6787: Rayna Mitchell
A6788: 90842 | B6788: 45869 | C6788: Davis Polk & Wardwell LLP | D6788: Olivia Gorfain | E6788: San Francisco | F6788: 0 | G6788: 0 | H6788: 0 | I6788: -1725 | J6788: 1725 | K6788: 0 | L6788: Torrey Carroll
A6789: 93204 | B6789: 45869 | C6789: County of Santa Clara | D6789: Lela Huenergardt | E6789: San Jose | F6789: 20555.21 | G6789: 0 | H6789: 20555.21 | I6789: 16001.26 | J6789: 4553.95 | K6789: 0.22154724 | L6789: Lela Huenergardt
A6790: 81826 | B6790: 45869 | C6790: WelbeHealth, LLC | D6790: Alex Blangeres | E6790: Sacramento | F6790: 0 | G6790: 0 | H6790: 0 | I6790: -165.39 | J6790: 165.39 | K6790: 0 | L6790: Farrah Race
A6791: 89622 | B6791: 45869 | C6791: Plumas District Hospital | D6791: Simon Sheppard | E6791: Sacramento | F6791: 0 | G6791: 0 | H6791: 0 | I6791: 395 | J6791: -395 | K6791: 0 | L6791: Andrea Greever
A6792: 90212 | B6792: 45869 | C6792: Longfellow Real Estate Partners LLC | D6792: Anthony Pantaleoni | E6792: San Francisco | F6792: 0 | G6792: -5056.09 | H6792: -5056.09 | I6792: 0 | J6792: -5056.09 | K6792: 1 | L6792: Anthony Pantaleoni,Melissa Rokes
A6793: 90530 | B6793: 45869 | C6793: Fenwick & West LLP | D6793: Kate Ingelstrom | E6793: San Jose | F6793: 0 | G6793: 2891.28 | H6793: 2891.28 | I6793: 1936 | J6793: 955.28 | K6793: 0.33040038 | L6793: Mary Sparacino
A6794: 91126 | B6794: 45869 | C6794: Simpson Thacher & Bartlett LLP | D6794: Olivia Gorfain | E6794: San Francisco | F6794: 0 | G6794: 0 | H6794: 0 | I6794: -55641.93 | J6794: 55641.93 | K6794: 0 | L6794: Anthony Pantaleoni
... A6823: 93772 | B6823: 45869 | C6823: Medley Partners Management LLC | D6823: Jill Marsh | E6823: San Francisco | F6823: 640 | G6823: 0 | H6823: 640 | I6823: 419.44 | J6823: 220.56 | K6823: 0.344625 | L6823: Chryslyn Perkins
A6824: 93777 | B6824: 45869 | C6824: Longfellow Real Estate Partners LLC | D6824: Anthony Pantaleoni | E6824: San Francisco | F6824: 10997.1 | G6824: 0 | H6824: 10997.1 | I6824: 0 | J6824: 10997.1 | K6824: 1
A6825: 93797 | B6825: 45869 | C6825: Intuit E-Commerce Orders | D6825: Norma Lopez | E6825: San Jose | F6825: 1651 | G6825: 0 | H6825: 1651 | I6825: 1265.4 | J6825: 385.6 | K6825: 0.23355542 | L6825: Norma Lopez
A6826: 93799 | B6826: 45869 | C6826: Intuit E-Commerce Orders | D6826: Norma Lopez | E6826: San Jose | F6826: 1651 | G6826: 0 | H6826: 1651 | I6826: 1291.4 | J6826: 359.6 | K6826: 0.21780739 | L6826: Norma Lopez
A6827: 93800 | B6827: 45869 | C6827: Intuit E-Commerce Orders | D6827: Norma Lopez | E6827: San Jose | F6827: 1215.6 | G6827: 0 | H6827: 1215.6 | I6827: 668.98 | J6827: 546.62 | K6827: 0.44967094 | L6827: Norma Lopez
A6828: 93801 | B6828: 45869 | C6828: Intuit E-Commerce Orders | D6828: Norma Lopez | E6828: San Jose | F6828: 1651 | G6828: 0 | H6828: 1651 | I6828: 1244.4 | J6828: 406.6 | K6828: 0.24627498 | L6828: Norma Lopez
A6829: 93814 | B6829: 45869 | C6829: PFM Health Sciences | D6829: Nick Christianson | E6829: San Jose | F6829: 6193.6 | G6829: 0 | H6829: 6193.6 | I6829: 4335.52 | J6829: 1858.08 | K6829: 0.3 | L6829: Carina Collison
A6830: 93818 | B6830: 45869 | C6830: Intuit-OR 205 | D6830: Norma Lopez | E6830: San Jose | F6830: 413.96 | G6830: 0 | H6830: 413.96 | I6830: 318.39 | J6830: 95.57 | K6830: 0.23086772 | L6830: Jessica Ramirez
A6831: 93825 | B6831: 45869 | C6831: YouTube, LLC | D6831: Olivia Gorfain | E6831: San Jose | F6831: 0 | G6831: 0 | H6831: 0 | I6831: 235.3 | J6831: -235.3 | K6831: 0 | L6831: Anthony Pantaleoni,Hana Estrada
A6832: 93827 | B6832: 45869 | C6832: Sequoia Capital Operations, LLC | D6832: Owen Cunningham | E6832: San Francisco | F6832: 323 | G6832: 0 | H6832: 323 | I6832: 223.54 | J6832: 99.46 | K6832: 0.3079257 | L6832: Kimi Katsuyoshi,Melissa Avalos
A6833: 93829 | B6833: 45869 | C6833: AAA Northern California, Utah & Nevada | D6833: Mark Dailey | E6833: Sacramento | F6833: 339 | G6833: 0 | H6833: 339 | I6833: 282.36 | J6833: 56.64 | K6833: 0.16707965 | L6833: Rayna Mitchell
A6834: 93846 | B6834: 45869 | C6834: Intuit E-Commerce Orders | D6834: Norma Lopez | E6834: San Jose | F6834: 2365.25 | G6834: 0 | H6834: 2365.25 | I6834: 1797.16 | J6834: 568.09 | K6834: 0.2401818 | L6834: Norma Lopez
A6835: 93849 | B6835: 45869 | C6835: Intuit E-Commerce Orders | D6835: Norma Lopez | E6835: San Jose | F6835: 1267.1 | G6835: 0 | H6835: 1267.1 | I6835: 977.98 | J6835: 289.12 | K6835: 0.22817457 | L6835: Norma Lopez
A6836: 86660 | B6836: 45870 | C6836: Levi Strauss & Co | D6836: Owen Cunningham | E6836: San Francisco | F6836: 0 | G6836: 0 | H6836: 0 | I6836: -389 | J6836: 389 | K6836: 0 | L6836: Josie Maitlen,Torrey Carroll
... A7786: 93877 | B7786: 45898 | C7786: Intuit-OR 205 | D7786: Norma Lopez | E7786: San Jose | F7786: 688 | G7786: 0 | H7786: 688 | I7786: 512 | J7786: 176 | K7786: 0.25581395 | L7786: Jessica Ramirez
...
